Workbook

Sheet Summary
A1: Riverstone month-end pack 2025 (built by copy and paste)
A3: month | B3: net_revenue | C3: target | D3: pct_of_target | E3: note
A4: Jan | B4: =SUMIFS(Jan!J2:J16,Jan!H2:H16,"<>Cancelled") | C4: 300000 | D4: =B4/C4
A5: Feb | B5: =SUMIFS(Feb!J2:J21,Feb!H2:H21,"<>Cancelled") | C5: 300000 | D5: =B5/C5
A6: Mar | B6: =SUM(Mar!J2:J19) | C6: 320000 | D6: =B6/C6
A7: Apr | B7: =SUM(Apr!J2:J22) | C7: 320000 | D7: =B7/C7
A8: May | B8: =SUMIFS(May!J2:J30,May!H2:H30,"<>Cancelled") | C8: 320000 | D8: =B8/C8
A9: Jun | B9: =SUMIFS(Jun!J2:J23,Jun!H2:H23,"<>Cancelled") | C9: 300000 | D9: =B9/C9
A10: Jul | B10: =SUMIFS(Jul!J2:J30,Jul!H2:H30,"<>Cancelled") | C10: 280000 | D10: =B10/C10
A11: Aug | B11: =SUMIFS(Aug!J2:J29,Aug!H2:H29,"<>Cancelled") | C11: 320000 | D11: =B11/C11
A12: Sep | B12: =SUMIFS(Sep!J2:J41,Sep!H2:H41,"<>Cancelled") | C12: 380000 | D12: =B12/C12
A13: Oct | B13: =SUMIFS(Oct!J2:J30,Oct!H2:H30,"<>Cancelled") | C13: 520000 | D13: =B13/C13
A14: Nov | B14: 633480 | C14: 500000 | D14: =B14/C14 | E14: typed from the flash email
A15: Dec | B15: =SUMIFS(Dec!J2:J41,Dec!H2:H41,"<>Cancelled") | C15: 380000 | D15: =B15/C15
A16: Total | B16: =SUM(B4:B15) | C16: =SUM(C4:C15) | D16: =B16/C16

Sheet Jan
A1: order_id | B1: order_date | C1: customer_code | D1: product_id | E1: quantity | F1: unit_price | G1: discount_pct | H1: status | I1: sales_rep | J1: net_revenue
A2: 10001 | B2: 45659 | C2: 0002 | D2: 108 | E2: 10 | F2: 290 | G2: 0 | H2: Delivered | I2: Neha Kulkarni | J2: =E2*F2*(1-G2/100)
A3: 10002 | B3: 45662 | C3: 0003 | D3: 107 | E3: 55 | F3: 380 | G3: 0 | H3: Delivered | I3: Farah Khan | J3: =E3*F3*(1-G3/100)
A4: 10003 | B4: 45669 | C4: 0005 | D4: 101 | E4: 25 | F4: 430 | G4: 0 | H4: Delivered | I4: Rahul Mehta | J4: =E4*F4*(1-G4/100)
A5: 10003 | B5: 45669 | C5: 0005 | D5: 102 | E5: 45 | F5: 750 | G5: 5 | H5: Delivered | I5: Rahul Mehta | J5: =E5*F5*(1-G5/100)
A6: 10003 | B6: 45669 | C6: 0005 | D6: 108 | E6: 10 | F6: 290 | G6: 0 | H6: Delivered | I6: Rahul Mehta | J6: =E6*F6*(1-G6/100)
A7: 10004 | B7: 45670 | C7: 0005 | D7: 101 | E7: 40 | F7: 430 | G7: 0 | H7: Delivered | I7: Rahul Mehta | J7: =E7*F7*(1-G7/100)
A8: 10004 | B8: 45670 | C8: 0005 | D8: 102 | E8: 15 | F8: 750 | G8: 5 | H8: Delivered | I8: Rahul Mehta | J8: =E8*F8*(1-G8/100)
A9: 10005 | B9: 45677 | C9: 0003 | D9: 101 | E9: 15 | F9: 430 | G9: 5 | H9: Delivered | I9: Farah Khan | J9: =E9*F9*(1-G9/100)
A10: 10006 | B10: 45678 | C10: 0004 | D10: 102 | E10: 25 | F10: 750 | G10: 5 | H10: Delivered | I10: Rahul Mehta | J10: =E10*F10*(1-G10/100)
A11: 10007 | B11: 45681 | C11: 0001 | D11: 101 | E11: 45 | F11: 430 | G11: 0 | H11: Delivered | I11: Neha Kulkarni | J11: =E11*F11*(1-G11/100)
A12: 10007 | B12: 45681 | C12: 0001 | D12: 102 | E12: 20 | F12: 750 | G12: 0 | H12: Delivered | I12: Neha Kulkarni | J12: =E12*F12*(1-G12/100)
A13: 10007 | B13: 45681 | C13: 0001 | D13: 108 | E13: 20 | F13: 290 | G13: 0 | H13: Delivered | I13: Neha Kulkarni | J13: =E13*F13*(1-G13/100)
... A16: 10008 | B16: 45683 | C16: 0001 | D16: 107 | E16: 25 | F16: 380 | G16: 0 | H16: Delivered | I16: Neha Kulkarni | J16: =E16*F16*(1-G16/100)

Sheet Feb
A1: order_id | B1: order_date | C1: customer_code | D1: product_id | E1: quantity | F1: unit_price | G1: discount_pct | H1: status | I1: sales_rep | J1: net_revenue
A2: 10009 | B2: 45690 | C2: 0010 | D2: 101 | E2: 30 | F2: 430 | G2: 0 | H2: Delivered | I2: Rahul Mehta | J2: =E2*F2*(1-G2/100)
A3: 10009 | B3: 45690 | C3: 0010 | D3: 102 | E3: 30 | F3: 750 | G3: 5 | H3: Delivered | I3: Rahul Mehta | J3: =E3*F3*(1-G3/100)
A4: 10010 | B4: 45693 | C4: 0001 | D4: 101 | E4: 20 | F4: 430 | G4: 0 | H4: Delivered | I4: Neha Kulkarni | J4: =E4*F4*(1-G4/100)
A5: 10010 | B5: 45693 | C5: 0001 | D5: 103 | E5: 10 | F5: 115 | G5: 0 | H5: Delivered | I5: Neha Kulkarni | J5: =E5*F5*(1-G5/100)
A6: 10010 | B6: 45693 | C6: 0001 | D6: 104 | E6: 35 | F6: 620 | G6: 0 | H6: Delivered | I6: Neha Kulkarni | J6: =E6*F6*(1-G6/100)
A7: 10011 | B7: 45704 | C7: 0003 | D7: 101 | E7: 25 | F7: 430 | G7: 0 | H7: Delivered | I7: Farah Khan | J7: =E7*F7*(1-G7/100)
A8: 10011 | B8: 45704 | C8: 0003 | D8: 107 | E8: 30 | F8: 380 | G8: 0 | H8: Delivered | I8: Farah Khan | J8: =E8*F8*(1-G8/100)
A9: 10011 | B9: 45704 | C9: 0003 | D9: 108 | E9: 30 | F9: 290 | G9: 5 | H9: Delivered | I9: Farah Khan | J9: =E9*F9*(1-G9/100)
A10: 10012 | B10: 45704 | C10: 0004 | D10: 105 | E10: 40 | F10: 1400 | G10: 12 | H10: Delivered | I10: Rahul Mehta | J10: =E10*F10*(1-G10/100)
A11: 10012 | B11: 45704 | C11: 0004 | D11: 108 | E11: 40 | F11: 290 | G11: 5 | H11: Delivered | I11: Rahul Mehta | J11: =E11*F11*(1-G11/100)
A12: 10013 | B12: 45705 | C12: 0007 | D12: 101 | E12: 30 | F12: 430 | G12: 5 | H12: Delivered | I12: Farah Khan | J12: =E12*F12*(1-G12/100)
A13: 10013 | B13: 45705 | C13: 0007 | D13: 108 | E13: 30 | F13: 290 | G13: 8 | H13: Delivered | I13: Farah Khan | J13: =E13*F13*(1-G13/100)
A14: 10014 | B14: 45705 | C14: 0007 | D14: 102 | E14: 25 | F14: 750 | G14: 8 | H14: Delivered | I14: Farah Khan | J14: =E14*F14*(1-G14/100)
A15: 10015 | B15: 45708 | C15: 0006 | D15: 108 | E15: 20 | F15: 290 | G15: 0 | H15: Delivered | J15: =E15*F15*(1-G15/100)
A16: 10016 | B16: 45708 | C16: 0012 | D16: 101 | E16: 25 | F16: 430 | G16: 0 | H16: Delivered | I16: Neha Kulkarni | J16: =E16*F16*(1-G16/100)
A17: 10016 | B17: 45708 | C17: 0012 | D17: 103 | E17: 50 | F17: 115 | G17: 5 | H17: Delivered | I17: Neha Kulkarni | J17: =E17*F17*(1-G17/100)
A18: 10016 | B18: 45708 | C18: 0012 | D18: 108 | E18: 30 | F18: 290 | G18: 0 | H18: Delivered | I18: Neha Kulkarni | J18: =E18*F18*(1-G18/100)
A19: 10017 | B19: 45713 | C19: 0005 | D19: 107 | E19: 40 | F19: 380 | G19: 5 | H19: Delivered | I19: Rahul Mehta | J19: =E19*F19*(1-G19/100)
A20: 10018 | B20: 45716 | C20: 0001 | D20: 101 | E20: 25 | F20: 430 | G20: 5 | H20: Delivered | I20: Neha Kulkarni | J20: =E20*F20*(1-G20/100)
A21: 10018 | B21: 45716 | C21: 0001 | D21: 108 | E21: 15 | F21: 290 | G21: 0 | H21: Delivered | I21: Neha Kulkarni | J21: =E21*F21*(1-G21/100)

Sheet Mar
A1: order_id | B1: order_date | C1: customer_code | D1: product_id | E1: quantity | F1: unit_price | G1: discount_pct | H1: status | I1: sales_rep | J1: net_revenue
A2: 10019 | B2: 45720 | C2: 0003 | D2: 103 | E2: 40 | F2: 115 | G2: 0 | H2: Delivered | I2: Farah Khan | J2: =E2*F2*(1-G2/100)
A3: 10019 | B3: 45720 | C3: 0003 | D3: 107 | E3: 35 | F3: 380 | G3: 5 | H3: Delivered | I3: Farah Khan | J3: =E3*F3*(1-G3/100)
A4: 10020 | B4: 45726 | C4: 0004 | D4: 101 | E4: 15 | F4: 430 | G4: 5 | H4: Delivered | I4: Rahul Mehta | J4: =E4*F4*(1-G4/100)
A5: 10020 | B5: 45726 | C5: 0004 | D5: 102 | E5: 15 | F5: 750 | G5: 12 | H5: Delivered | I5: Rahul Mehta | J5: =E5*F5*(1-G5/100)
A6: 10020 | B6: 45726 | C6: 0004 | D6: 105 | E6: 25 | F6: 1400 | G6: 10 | H6: Delivered | I6: Rahul Mehta | J6: =E6*F6*(1-G6/100)
A7: 10021 | B7: 45734 | C7: 0005 | D7: 104 | E7: 15 | F7: 620 | G7: 0 | H7: Delivered | I7: Rahul Mehta | J7: =E7*F7*(1-G7/100)
A8: 10022 | B8: 45737 | C8: 0001 | D8: 102 | E8: 45 | F8: 750 | G8: 0 | H8: Delivered | I8: Neha Kulkarni | J8: =E8*F8*(1-G8/100)
A9: 10022 | B9: 45737 | C9: 0001 | D9: 107 | E9: 15 | F9: 380 | G9: 0 | H9: Delivered | I9: Neha Kulkarni | J9: =E9*F9*(1-G9/100)
A10: 10023 | B10: 45737 | C10: 0008 | D10: 108 | E10: 10 | F10: 290 | G10: 0 | H10: Delivered | I10: Neha Kulkarni | J10: =E10*F10*(1-G10/100)
A11: 10024 | B11: 45738 | C11: 0007 | D11: 101 | E11: 35 | F11: 430 | G11: 10 | H11: Delivered | I11: Farah Khan | J11: =E11*F11*(1-G11/100)
A12: 10024 | B12: 45738 | C12: 0007 | D12: 102 | E12: 20 | F12: 750 | G12: 5 | H12: Delivered | I12: Farah Khan | J12: =E12*F12*(1-G12/100)
A13: 10025 | B13: 45738 | C13: 0010 | D13: 102 | E13: 30 | F13: 750 | G13: 5 | H13: Delivered | I13: Rahul Mehta | J13: =E13*F13*(1-G13/100)
... A19: 10029 | B19: 45744 | C19: 0002 | D19: 106 | E19: 15 | F19: 1150 | G19: 5 | H19: Delivered | I19: Neha Kulkarni | J19: =E19*F19*(1-G19/100)

Sheet Apr
A1: order_id | B1: order_date | C1: customer_code | D1: product_id | E1: quantity | F1: unit_price | G1: discount_pct | H1: status | I1: sales_rep | J1: net_revenue
A2: 10030 | B2: 45755 | C2: 0005 | D2: 107 | E2: 35 | F2: 380 | G2: 5 | H2: Delivered | I2: Rahul Mehta | J2: =E2*F2*(1-G2/100)
A3: 10031 | B3: 45756 | C3: 0011 | D3: 101 | E3: 15 | F3: 430 | G3: 8 | H3: Delivered | I3: Rahul Mehta | J3: =E3*F3*(1-G3/100)
A4: 10032 | B4: 45758 | C4: 0002 | D4: 101 | E4: 30 | F4: 430 | G4: 0 | H4: Delivered | I4: Neha Kulkarni | J4: =E4*F4*(1-G4/100)
A5: 10032 | B5: 45758 | C5: 0002 | D5: 103 | E5: 35 | F5: 115 | G5: 0 | H5: Delivered | I5: Neha Kulkarni | J5: =E5*F5*(1-G5/100)
A6: 10032 | B6: 45758 | C6: 0002 | D6: 108 | E6: 10 | F6: 290 | G6: 0 | H6: Delivered | I6: Neha Kulkarni | J6: =E6*F6*(1-G6/100)
A7: 10033 | B7: 45758 | C7: 0003 | D7: 104 | E7: 10 | F7: 620 | G7: 5 | H7: Delivered | I7: Farah Khan | J7: =E7*F7*(1-G7/100)
A8: 10033 | B8: 45758 | C8: 0003 | D8: 107 | E8: 20 | F8: 380 | G8: 5 | H8: Delivered | I8: Farah Khan | J8: =E8*F8*(1-G8/100)
A9: 10034 | B9: 45760 | C9: 0010 | D9: 104 | E9: 40 | F9: 620 | G9: 0 | H9: Cancelled | I9: Rahul Mehta | J9: =E9*F9*(1-G9/100)
A10: 10035 | B10: 45761 | C10: 0003 | D10: 101 | E10: 25 | F10: 430 | G10: 5 | H10: Delivered | I10: Farah Khan | J10: =E10*F10*(1-G10/100)
A11: 10036 | B11: 45762 | C11: 0012 | D11: 103 | E11: 35 | F11: 115 | G11: 0 | H11: Delivered | J11: =E11*F11*(1-G11/100)
A12: 10036 | B12: 45762 | C12: 0012 | D12: 104 | E12: 30 | F12: 620 | G12: 5 | H12: Delivered | J12: =E12*F12*(1-G12/100)
A13: 10036 | B13: 45762 | C13: 0012 | D13: 107 | E13: 35 | F13: 380 | G13: 0 | H13: Delivered | J13: =E13*F13*(1-G13/100)
A14: 10037 | B14: 45767 | C14: 0005 | D14: 101 | E14: 45 | F14: 430 | G14: 0 | H14: Delivered | I14: Rahul Mehta | J14: =E14*F14*(1-G14/100)
A15: 10037 | B15: 45767 | C15: 0005 | D15: 108 | E15: 30 | F15: 290 | G15: 5 | H15: Delivered | I15: Rahul Mehta | J15: =E15*F15*(1-G15/100)
A16: 10038 | B16: 45768 | C16: 0006 | D16: 107 | E16: 50 | F16: 380 | G16: 0 | H16: Delivered | J16: =E16*F16*(1-G16/100)
A17: 10039 | B17: 45769 | C17: 0001 | D17: 102 | E17: 15 | F17: 750 | G17: 5 | H17: Delivered | I17: Neha Kulkarni | J17: =E17*F17*(1-G17/100)
A18: 10039 | B18: 45769 | C18: 0001 | D18: 104 | E18: 35 | F18: 620 | G18: 0 | H18: Delivered | I18: Neha Kulkarni | J18: =E18*F18*(1-G18/100)
A19: 10040 | B19: 45770 | C19: 0004 | D19: 108 | E19: 25 | F19: 290 | G19: 5 | H19: Delivered | I19: Rahul Mehta | J19: =E19*F19*(1-G19/100)
A20: 10041 | B20: 45770 | C20: 0012 | D20: 103 | E20: 35 | F20: 115 | G20: 0 | H20: Delivered | I20: Neha Kulkarni | J20: =E20*F20*(1-G20/100)
A21: 10041 | B21: 45770 | C21: 0012 | D21: 108 | E21: 60 | F21: 290 | G21: 5 | H21: Delivered | I21: Neha Kulkarni | J21: =E21*F21*(1-G21/100)
A22: 10042 | B22: 45772 | C22: 0007 | D22: 102 | E22: 10 | F22: 750 | G22: 5 | H22: Delivered | I22: Farah Khan | J22: =E22*F22*(1-G22/100)

Sheet May
A1: order_id | B1: order_date | C1: customer_code | D1: product_id | E1: quantity | F1: unit_price | G1: discount_pct | H1: status | I1: sales_rep | J1: net_revenue
A2: 10043 | B2: 45781 | C2: 0002 | D2: 102 | E2: 15 | F2: 750 | G2: 0 | H2: Delivered | I2: Neha Kulkarni | J2: =E2*F2*(1-G2/100)
A3: 10043 | B3: 45781 | C3: 0002 | D3: 104 | E3: 20 | F3: 620 | G3: 0 | H3: Delivered | I3: Neha Kulkarni | J3: =E3*F3*(1-G3/100)
A4: 10044 | B4: 45781 | C4: 0004 | D4: 101 | E4: 15 | F4: 430 | G4: 8 | H4: Delivered | I4: Rahul Mehta | J4: =E4*F4*(1-G4/100)
A5: 10044 | B5: 45781 | C5: 0004 | D5: 105 | E5: 35 | F5: 1400 | G5: 10 | H5: Delivered | I5: Rahul Mehta | J5: =E5*F5*(1-G5/100)
A6: 10044 | B6: 45781 | C6: 0004 | D6: 108 | E6: 5 | F6: 290 | G6: 12 | H6: Delivered | I6: Rahul Mehta | J6: =E6*F6*(1-G6/100)
A7: 10045 | B7: 45781 | C7: 0013 | D7: 102 | E7: 25 | F7: 750 | G7: 0 | H7: Delivered | I7: Neha Kulkarni | J7: =E7*F7*(1-G7/100)
A8: 10045 | B8: 45781 | C8: 0013 | D8: 103 | E8: 35 | F8: 115 | G8: 0 | H8: Delivered | I8: Neha Kulkarni | J8: =E8*F8*(1-G8/100)
A9: 10046 | B9: 45783 | C9: 0014 | D9: 101 | E9: 15 | F9: 430 | G9: 10 | H9: Delivered | I9: Farah Khan | J9: =E9*F9*(1-G9/100)
A10: 10047 | B10: 45784 | C10: 0001 | D10: 106 | E10: 15 | F10: 1150 | G10: 0 | H10: Delivered | I10: Neha Kulkarni | J10: =E10*F10*(1-G10/100)
A11: 10048 | B11: 45785 | C11: 0005 | D11: 103 | E11: 20 | F11: 115 | G11: 0 | H11: Delivered | I11: Rahul Mehta | J11: =E11*F11*(1-G11/100)
A12: 10048 | B12: 45785 | C12: 0005 | D12: 107 | E12: 15 | F12: 380 | G12: 0 | H12: Delivered | I12: Rahul Mehta | J12: =E12*F12*(1-G12/100)
A13: 10049 | B13: 45790 | C13: 0007 | D13: 102 | E13: 20 | F13: 750 | G13: 12 | H13: Delivered | I13: Farah Khan | J13: =E13*F13*(1-G13/100)
... A25: 10053 | B25: 45797 | C25: 0003 | D25: 108 | E25: 50 | F25: 290 | G25: 5 | H25: Delivered | I25: Farah Khan | J25: =E25*F25*(1-G25/100)
A26: 10054 | B26: 45798 | C26: 0006 | D26: 107 | E26: 35 | F26: 380 | G26: 5 | H26: Delivered | J26: =E26*F26*(1-G26/100)
A27: 10055 | B27: 45798 | C27: 0008 | D27: 103 | E27: 20 | F27: 115 | G27: 0 | H27: Delivered | I27: Neha Kulkarni | J27: =E27*F27*(1-G27/100)
A28: 10056 | B28: 45799 | C28: 0009 | D28: 103 | E28: 25 | F28: 115 | G28: 5 | H28: Delivered | I28: Farah Khan | J28: =E28*F28*(1-G28/100)
A29: 10056 | B29: 45799 | C29: 0009 | D29: 108 | E29: 30 | F29: 290 | G29: 5 | H29: Delivered | I29: Farah Khan | J29: =E29*F29*(1-G29/100)
A30: 10057 | B30: 45804 | C30: 0011 | D30: 105 | E30: 35 | F30: 1400 | G30: 10 | H30: Delivered | I30: Rahul Mehta | J30: =E30*F30*(1-G30/100)

Sheet Jun
A1: order_id | B1: order_date | C1: customer_code | D1: product_id | E1: quantity | F1: unit_price | G1: discount_pct | H1: status | I1: sales_rep | J1: net_revenue
A2: 10058 | B2: 45809 | C2: 0012 | D2: 101 | E2: 30 | F2: 430 | G2: 0 | H2: Delivered | I2: Neha Kulkarni | J2: =E2*F2*(1-G2/100)
A3: 10058 | B3: 45809 | C3: 0012 | D3: 108 | E3: 25 | F3: 290 | G3: 5 | H3: Delivered | I3: Neha Kulkarni | J3: =E3*F3*(1-G3/100)
A4: 10059 | B4: 45812 | C4: 0001 | D4: 102 | E4: 5 | F4: 750 | G4: 0 | H4: Delivered | I4: Neha Kulkarni | J4: =E4*F4*(1-G4/100)
A5: 10060 | B5: 45814 | C5: 0004 | D5: 108 | E5: 30 | F5: 290 | G5: 5 | H5: Delivered | I5: Rahul Mehta | J5: =E5*F5*(1-G5/100)
A6: 10061 | B6: 45817 | C6: 0015 | D6: 108 | E6: 5 | F6: 290 | G6: 5 | H6: Delivered | I6: Farah Khan | J6: =E6*F6*(1-G6/100)
A7: 10062 | B7: 45818 | C7: 0002 | D7: 104 | E7: 10 | F7: 620 | G7: 5 | H7: Delivered | I7: Neha Kulkarni | J7: =E7*F7*(1-G7/100)
A8: 10062 | B8: 45818 | C8: 0002 | D8: 108 | E8: 30 | F8: 290 | G8: 5 | H8: Delivered | I8: Neha Kulkarni | J8: =E8*F8*(1-G8/100)
A9: 10063 | B9: 45818 | C9: 0006 | D9: 101 | E9: 20 | F9: 430 | G9: 0 | H9: Delivered | J9: =E9*F9*(1-G9/100)
A10: 10063 | B10: 45818 | C10: 0006 | D10: 103 | E10: 15 | F10: 115 | G10: 5 | H10: Delivered | J10: =E10*F10*(1-G10/100)
A11: 10064 | B11: 45818 | C11: 0011 | D11: 101 | E11: 15 | F11: 430 | G11: 12 | H11: Delivered | I11: Rahul Mehta | J11: =E11*F11*(1-G11/100)
A12: 10064 | B12: 45818 | C12: 0011 | D12: 102 | E12: 15 | F12: 750 | G12: 5 | H12: Delivered | I12: Rahul Mehta | J12: =E12*F12*(1-G12/100)
A13: 10064 | B13: 45818 | C13: 0011 | D13: 105 | E13: 5 | F13: 1400 | G13: 12 | H13: Delivered | I13: Rahul Mehta | J13: =E13*F13*(1-G13/100)
A14: 10065 | B14: 45818 | C14: 0015 | D14: 101 | E14: 5 | F14: 430 | G14: 5 | H14: Delivered | I14: Farah Khan | J14: =E14*F14*(1-G14/100)
A15: 10066 | B15: 45821 | C15: 0007 | D15: 105 | E15: 20 | F15: 1400 | G15: 5 | H15: Delivered | I15: Farah Khan | J15: =E15*F15*(1-G15/100)
A16: 10066 | B16: 45821 | C16: 0007 | D16: 108 | E16: 15 | F16: 290 | G16: 8 | H16: Delivered | I16: Farah Khan | J16: =E16*F16*(1-G16/100)
A17: 10067 | B17: 45822 | C17: 0013 | D17: 103 | E17: 25 | F17: 115 | G17: 5 | H17: Delivered | I17: Neha Kulkarni | J17: =E17*F17*(1-G17/100)
A18: 10067 | B18: 45822 | C18: 0013 | D18: 108 | E18: 25 | F18: 290 | G18: 0 | H18: Delivered | I18: Neha Kulkarni | J18: =E18*F18*(1-G18/100)
A19: 10068 | B19: 45826 | C19: 0005 | D19: 101 | E19: 15 | F19: 430 | G19: 0 | H19: Delivered | I19: Rahul Mehta | J19: =E19*F19*(1-G19/100)
A20: 10069 | B20: 45832 | C20: 0003 | D20: 101 | E20: 20 | F20: 430 | G20: 0 | H20: Delivered | I20: Farah Khan | J20: =E20*F20*(1-G20/100)
A21: 10069 | B21: 45832 | C21: 0003 | D21: 104 | E21: 25 | F21: 620 | G21: 5 | H21: Delivered | I21: Farah Khan | J21: =E21*F21*(1-G21/100)
A22: 10070 | B22: 45836 | C22: 0014 | D22: 105 | E22: 20 | F22: 1400 | G22: 5 | H22: Delivered | I22: Farah Khan | J22: =E22*F22*(1-G22/100)
A23: 10070 | B23: 45836 | C23: 0014 | D23: 108 | E23: 30 | F23: 290 | G23: 10 | H23: Delivered | I23: Farah Khan | J23: =E23*F23*(1-G23/100)

Sheet Jul
A1: order_id | B1: order_date | C1: customer_code | D1: product_id | E1: quantity | F1: unit_price | G1: discount_pct | H1: status | I1: sales_rep | J1: net_revenue
A2: 10071 | B2: 45841 | C2: 0015 | D2: 104 | E2: 30 | F2: 620 | G2: 0 | H2: Delivered | I2: Farah Khan | J2: =E2*F2*(1-G2/100)
A3: 10071 | B3: 45841 | C3: 0015 | D3: 107 | E3: 25 | F3: 380 | G3: 5 | H3: Delivered | I3: Farah Khan | J3: =E3*F3*(1-G3/100)
A4: 10071 | B4: 45841 | C4: 0015 | D4: 108 | E4: 25 | F4: 290 | G4: 5 | H4: Delivered | I4: Farah Khan | J4: =E4*F4*(1-G4/100)
A5: 10072 | B5: 45845 | C5: 0003 | D5: 107 | E5: 35 | F5: 380 | G5: 0 | H5: Delivered | I5: Farah Khan | J5: =E5*F5*(1-G5/100)
A6: 10073 | B6: 45848 | C6: 0005 | D6: 103 | E6: 5 | F6: 115 | G6: 0 | H6: Delivered | I6: Rahul Mehta | J6: =E6*F6*(1-G6/100)
A7: 10073 | B7: 45848 | C7: 0005 | D7: 104 | E7: 20 | F7: 620 | G7: 5 | H7: Delivered | I7: Rahul Mehta | J7: =E7*F7*(1-G7/100)
A8: 10074 | B8: 45853 | C8: 0008 | D8: 104 | E8: 15 | F8: 620 | G8: 0 | H8: Delivered | I8: Neha Kulkarni | J8: =E8*F8*(1-G8/100)
A9: 10074 | B9: 45853 | C9: 0008 | D9: 107 | E9: 20 | F9: 380 | G9: 0 | H9: Delivered | I9: Neha Kulkarni | J9: =E9*F9*(1-G9/100)
A10: 10075 | B10: 45853 | C10: 0012 | D10: 101 | E10: 20 | F10: 430 | G10: 0 | H10: Delivered | I10: Neha Kulkarni | J10: =E10*F10*(1-G10/100)
A11: 10075 | B11: 45853 | C11: 0012 | D11: 104 | E11: 20 | F11: 620 | G11: 0 | H11: Delivered | I11: Neha Kulkarni | J11: =E11*F11*(1-G11/100)
A12: 10075 | B12: 45853 | C12: 0012 | D12: 107 | E12: 5 | F12: 380 | G12: 5 | H12: Delivered | I12: Neha Kulkarni | J12: =E12*F12*(1-G12/100)
A13: 10076 | B13: 45858 | C13: 0015 | D13: 103 | E13: 5 | F13: 115 | G13: 5 | H13: Delivered | I13: Farah Khan | J13: =E13*F13*(1-G13/100)
... A30: 10083 | B30: 45864 | C30: 0011 | D30: 108 | E30: 15 | F30: 290 | G30: 10 | H30: Delivered | I30: Rahul Mehta | J30: =E30*F30*(1-G30/100)

Sheet Aug
A1: order_id | B1: order_date | C1: customer_code | D1: product_id | E1: quantity | F1: unit_price | G1: discount_pct | H1: status | I1: sales_rep | J1: net_revenue
A2: 10084 | B2: 45872 | C2: 0003 | D2: 101 | E2: 40 | F2: 430 | G2: 5 | H2: Delivered | I2: Farah Khan | J2: =E2*F2*(1-G2/100)
A3: 10084 | B3: 45872 | C3: 0003 | D3: 104 | E3: 15 | F3: 620 | G3: 0 | H3: Delivered | I3: Farah Khan | J3: =E3*F3*(1-G3/100)
A4: 10085 | B4: 45873 | C4: 0018 | D4: 101 | E4: 15 | F4: 430 | G4: 0 | H4: Delivered | I4: Rahul Mehta | J4: =E4*F4*(1-G4/100)
A5: 10085 | B5: 45873 | C5: 0018 | D5: 102 | E5: 20 | F5: 750 | G5: 5 | H5: Delivered | I5: Rahul Mehta | J5: =E5*F5*(1-G5/100)
A6: 10085 | B6: 45873 | C6: 0018 | D6: 103 | E6: 40 | F6: 115 | G6: 5 | H6: Delivered | I6: Rahul Mehta | J6: =E6*F6*(1-G6/100)
A7: 10086 | B7: 45880 | C7: 0005 | D7: 107 | E7: 40 | F7: 380 | G7: 0 | H7: Delivered | I7: Rahul Mehta | J7: =E7*F7*(1-G7/100)
A8: 10086 | B8: 45880 | C8: 0005 | D8: 108 | E8: 25 | F8: 290 | G8: 0 | H8: Delivered | I8: Rahul Mehta | J8: =E8*F8*(1-G8/100)
A9: 10087 | B9: 45880 | C9: 0014 | D9: 101 | E9: 10 | F9: 430 | G9: 10 | H9: Delivered | I9: Farah Khan | J9: =E9*F9*(1-G9/100)
A10: 10087 | B10: 45880 | C10: 0014 | D10: 102 | E10: 15 | F10: 750 | G10: 12 | H10: Delivered | I10: Farah Khan | J10: =E10*F10*(1-G10/100)
A11: 10087 | B11: 45880 | C11: 0014 | D11: 105 | E11: 25 | F11: 1400 | G11: 12 | H11: Delivered | I11: Farah Khan | J11: =E11*F11*(1-G11/100)
A12: 10088 | B12: 45881 | C12: 0001 | D12: 101 | E12: 35 | F12: 430 | G12: 5 | H12: Delivered | I12: Neha Kulkarni | J12: =E12*F12*(1-G12/100)
A13: 10088 | B13: 45881 | C13: 0001 | D13: 103 | E13: 40 | F13: 115 | G13: 0 | H13: Delivered | I13: Neha Kulkarni | J13: =E13*F13*(1-G13/100)
... A29: 10097 | B29: 45896 | C29: 0007 | D29: 108 | E29: 10 | F29: 290 | G29: 10 | H29: Delivered | I29: Farah Khan | J29: =E29*F29*(1-G29/100)

Sheet Sep
A1: order_id | B1: order_date | C1: customer_code | D1: product_id | E1: quantity | F1: unit_price | G1: discount_pct | H1: status | I1: sales_rep | J1: net_revenue
A2: 10098 | B2: 45902 | C2: 0018 | D2: 101 | E2: 40 | F2: 430 | G2: 0 | H2: Delivered | I2: Rahul Mehta | J2: =E2*F2*(1-G2/100)
A3: 10098 | B3: 45902 | C3: 0018 | D3: 108 | E3: 10 | F3: 290 | G3: 0 | H3: Delivered | I3: Rahul Mehta | J3: =E3*F3*(1-G3/100)
A4: 10099 | B4: 45902 | C4: 0019 | D4: 102 | E4: 15 | F4: 750 | G4: 5 | H4: Delivered | I4: Farah Khan | J4: =E4*F4*(1-G4/100)
A5: 10099 | B5: 45902 | C5: 0019 | D5: 105 | E5: 35 | F5: 1400 | G5: 10 | H5: Delivered | I5: Farah Khan | J5: =E5*F5*(1-G5/100)
A6: 10099 | B6: 45902 | C6: 0019 | D6: 108 | E6: 15 | F6: 290 | G6: 5 | H6: Delivered | I6: Farah Khan | J6: =E6*F6*(1-G6/100)
A7: 10100 | B7: 45903 | C7: 0021 | D7: 101 | E7: 15 | F7: 430 | G7: 5 | H7: Delivered | I7: Rahul Mehta | J7: =E7*F7*(1-G7/100)
A8: 10100 | B8: 45903 | C8: 0021 | D8: 104 | E8: 35 | F8: 620 | G8: 0 | H8: Delivered | I8: Rahul Mehta | J8: =E8*F8*(1-G8/100)
A9: 10100 | B9: 45903 | C9: 0021 | D9: 108 | E9: 20 | F9: 290 | G9: 0 | H9: Delivered | I9: Rahul Mehta | J9: =E9*F9*(1-G9/100)
A10: 10101 | B10: 45907 | C10: 0014 | D10: 101 | E10: 10 | F10: 430 | G10: 12 | H10: Delivered | I10: Farah Khan | J10: =E10*F10*(1-G10/100)
A11: 10101 | B11: 45907 | C11: 0014 | D11: 105 | E11: 35 | F11: 1400 | G11: 5 | H11: Delivered | I11: Farah Khan | J11: =E11*F11*(1-G11/100)
A12: 10102 | B12: 45909 | C12: 0017 | D12: 101 | E12: 10 | F12: 430 | G12: 5 | H12: Delivered | I12: Neha Kulkarni | J12: =E12*F12*(1-G12/100)
A13: 10102 | B13: 45909 | C13: 0017 | D13: 107 | E13: 25 | F13: 380 | G13: 0 | H13: Delivered | I13: Neha Kulkarni | J13: =E13*F13*(1-G13/100)
... A24: 10107 | B24: 45913 | C24: 0014 | D24: 105 | E24: 45 | F24: 1400 | G24: 10 | H24: Delivered | I24: Farah Khan | J24: =E24*F24*(1-G24/100)
A25: 10108 | B25: 45915 | C25: 0022 | D25: 101 | E25: 30 | F25: 430 | G25: 0 | H25: Delivered | J25: =E25*F25*(1-G25/100)
A26: 10108 | B26: 45915 | C26: 0022 | D26: 107 | E26: 35 | F26: 380 | G26: 0 | H26: Delivered | J26: =E26*F26*(1-G26/100)
A27: 10109 | B27: 45918 | C27: 0009 | D27: 107 | E27: 15 | F27: 380 | G27: 0 | H27: Delivered | I27: Farah Khan | J27: =E27*F27*(1-G27/100)
A28: 10109 | B28: 45918 | C28: 0009 | D28: 108 | E28: 35 | F28: 290 | G28: 0 | H28: Delivered | I28: Farah Khan | J28: =E28*F28*(1-G28/100)
A29: 10110 | B29: 45921 | C29: 0001 | D29: 104 | E29: 35 | F29: 620 | G29: 0 | H29: Delivered | I29: Neha Kulkarni | J29: =E29*F29*(1-G29/100)
A30: 10110 | B30: 45921 | C30: 0001 | D30: 107 | E30: 25 | F30: 380 | G30: 5 | H30: Delivered | I30: Neha Kulkarni | J30: =E30*F30*(1-G30/100)
A31: 10111 | B31: 45922 | C31: 0003 | D31: 101 | E31: 30 | F31: 430 | G31: 0 | H31: Delivered | I31: Farah Khan | J31: =E31*F31*(1-G31/100)
A32: 10112 | B32: 45922 | C32: 0003 | D32: 101 | E32: 10 | F32: 430 | G32: 5 | H32: Delivered | I32: Farah Khan | J32: =E32*F32*(1-G32/100)
A33: 10112 | B33: 45922 | C33: 0003 | D33: 104 | E33: 15 | F33: 620 | G33: 5 | H33: Delivered | I33: Farah Khan | J33: =E33*F33*(1-G33/100)
A34: 10112 | B34: 45922 | C34: 0003 | D34: 107 | E34: 60 | F34: 380 | G34: 5 | H34: Delivered | I34: Farah Khan | J34: =E34*F34*(1-G34/100)
A35: 10113 | B35: 45923 | C35: 0005 | D35: 101 | E35: 25 | F35: 430 | G35: 5 | H35: Delivered | I35: Rahul Mehta | J35: =E35*F35*(1-G35/100)
A36: 10113 | B36: 45923 | C36: 0005 | D36: 102 | E36: 10 | F36: 750 | G36: 0 | H36: Delivered | I36: Rahul Mehta | J36: =E36*F36*(1-G36/100)
A37: 10113 | B37: 45923 | C37: 0005 | D37: 107 | E37: 20 | F37: 380 | G37: 5 | H37: Delivered | I37: Rahul Mehta | J37: =E37*F37*(1-G37/100)
A38: 10114 | B38: 45924 | C38: 0007 | D38: 101 | E38: 25 | F38: 430 | G38: 12 | H38: Delivered | I38: Farah Khan | J38: =E38*F38*(1-G38/100)
... A41: 10115 | B41: 45928 | C41: 0015 | D41: 107 | E41: 20 | F41: 380 | G41: 0 | H41: Delivered | I41: Farah Khan | J41: =E41*F41*(1-G41/100)

Sheet Oct
A1: order_id | B1: order_date | C1: customer_code | D1: product_id | E1: quantity | F1: unit_price | G1: discount_pct | H1: status | I1: sales_rep | J1: net_revenue
A2: 10116 | B2: 45932 | C2: 0005 | D2: 101 | E2: 20 | F2: 430 | G2: 0 | H2: Delivered | I2: Rahul Mehta | J2: =E2*F2*(1-G2/100)
A3: 10116 | B3: 45932 | C3: 0005 | D3: 102 | E3: 60 | F3: 750 | G3: 0 | H3: Delivered | I3: Rahul Mehta | J3: =E3*F3*(1-G3/100)
A4: 10116 | B4: 45932 | C4: 0005 | D4: 103 | E4: 30 | F4: 115 | G4: 0 | H4: Delivered | I4: Rahul Mehta | J4: =E4*F4*(1-G4/100)
A5: 10117 | B5: 45932 | C5: 0021 | D5: 102 | E5: 15 | F5: 750 | G5: 0 | H5: Delivered | I5: Rahul Mehta | J5: =E5*F5*(1-G5/100)
A6: 10117 | B6: 45932 | C6: 0021 | D6: 107 | E6: 65 | F6: 380 | G6: 0 | H6: Delivered | I6: Rahul Mehta | J6: =E6*F6*(1-G6/100)
A7: 10118 | B7: 45933 | C7: 0003 | D7: 103 | E7: 80 | F7: 115 | G7: 0 | H7: Delivered | I7: Farah Khan | J7: =E7*F7*(1-G7/100)
A8: 10118 | B8: 45933 | C8: 0003 | D8: 107 | E8: 85 | F8: 380 | G8: 0 | H8: Delivered | I8: Farah Khan | J8: =E8*F8*(1-G8/100)
A9: 10119 | B9: 45933 | C9: 0012 | D9: 101 | E9: 80 | F9: 430 | G9: 5 | H9: Delivered | I9: Neha Kulkarni | J9: =E9*F9*(1-G9/100)
A10: 10119 | B10: 45933 | C10: 0012 | D10: 107 | E10: 65 | F10: 380 | G10: 0 | H10: Delivered | I10: Neha Kulkarni | J10: =E10*F10*(1-G10/100)
A11: 10120 | B11: 45935 | C11: 0003 | D11: 103 | E11: 40 | F11: 115 | G11: 0 | H11: Delivered | I11: Farah Khan | J11: =E11*F11*(1-G11/100)
A12: 10120 | B12: 45935 | C12: 0003 | D12: 108 | E12: 20 | F12: 290 | G12: 0 | H12: Delivered | I12: Farah Khan | J12: =E12*F12*(1-G12/100)
A13: 10121 | B13: 45936 | C13: 0023 | D13: 107 | E13: 55 | F13: 380 | G13: 5 | H13: Delivered | I13: Farah Khan | J13: =E13*F13*(1-G13/100)
... A29: 10130 | B29: 45948 | C29: 0007 | D29: 102 | E29: 20 | F29: 750 | G29: 10 | H29: Delivered | I29: Farah Khan | J29: =E29*F29*(1-G29/100)
A30: 10131 | B30: 45948 | C30: 0022 | D30: 103 | E30: 70 | F30: 115 | G30: 0 | H30: Cancelled | J30: =E30*F30*(1-G30/100)
A31: 10131 | B31: 45948 | C31: 0022 | D31: 107 | E31: 25 | F31: 380 | G31: 0 | H31: Cancelled | J31: =E31*F31*(1-G31/100)
A32: 10131 | B32: 45948 | C32: 0022 | D32: 108 | E32: 70 | F32: 290 | G32: 0 | H32: Cancelled | J32: =E32*F32*(1-G32/100)
A33: 10132 | B33: 45950 | C33: 0001 | D33: 101 | E33: 65 | F33: 430 | G33: 0 | H33: Delivered | I33: Neha Kulkarni | J33: =E33*F33*(1-G33/100)
A34: 10133 | B34: 45955 | C34: 0001 | D34: 102 | E34: 70 | F34: 750 | G34: 5 | H34: Delivered | I34: Neha Kulkarni | J34: =E34*F34*(1-G34/100)
A35: 10133 | B35: 45955 | C35: 0001 | D35: 107 | E35: 50 | F35: 380 | G35: 0 | H35: Delivered | I35: Neha Kulkarni | J35: =E35*F35*(1-G35/100)
A36: 10134 | B36: 45956 | C36: 0020 | D36: 103 | E36: 50 | F36: 115 | G36: 0 | H36: Delivered | I36: Neha Kulkarni | J36: =E36*F36*(1-G36/100)
A37: 10135 | B37: 45957 | C37: 0004 | D37: 102 | E37: 15 | F37: 750 | G37: 12 | H37: Delivered | I37: Rahul Mehta | J37: =E37*F37*(1-G37/100)
A38: 10135 | B38: 45957 | C38: 0004 | D38: 108 | E38: 40 | F38: 290 | G38: 12 | H38: Delivered | I38: Rahul Mehta | J38: =E38*F38*(1-G38/100)
A39: 10136 | B39: 45957 | C39: 0019 | D39: 108 | E39: 50 | F39: 290 | G39: 8 | H39: Delivered | I39: Farah Khan | J39: =E39*F39*(1-G39/100)

Sheet Nov
A1: order_id | B1: order_date | C1: customer_code | D1: product_id | E1: quantity | F1: unit_price | G1: discount_pct | H1: status | I1: sales_rep | J1: net_revenue
A2: 10137 | B2: 45965 | C2: 0012 | D2: 108 | E2: 15 | F2: 290 | G2: 5 | H2: Delivered | I2: Neha Kulkarni | J2: =E2*F2*(1-G2/100)
A3: 10138 | B3: 45966 | C3: 0003 | D3: 103 | E3: 15 | F3: 115 | G3: 5 | H3: Delivered | I3: Farah Khan | J3: =E3*F3*(1-G3/100)
A4: 10138 | B4: 45966 | C4: 0003 | D4: 108 | E4: 55 | F4: 290 | G4: 0 | H4: Delivered | I4: Farah Khan | J4: =E4*F4*(1-G4/100)
A5: 10139 | B5: 45967 | C5: 0011 | D5: 101 | E5: 60 | F5: 430 | G5: 8 | H5: Delivered | I5: Rahul Mehta | J5: =E5*F5*(1-G5/100)
A6: 10139 | B6: 45967 | C6: 0011 | D6: 105 | E6: 20 | F6: 1400 | G6: 12 | H6: Delivered | I6: Rahul Mehta | J6: =E6*F6*(1-G6/100)
A7: 10140 | B7: 45970 | C7: 0002 | D7: 103 | E7: 65 | F7: 115 | G7: 0 | H7: Delivered | I7: Neha Kulkarni | J7: =E7*F7*(1-G7/100)
A8: 10140 | B8: 45970 | C8: 0002 | D8: 104 | E8: 55 | F8: 620 | G8: 5 | H8: Delivered | I8: Neha Kulkarni | J8: =E8*F8*(1-G8/100)
A9: 10141 | B9: 45970 | C9: 0008 | D9: 104 | E9: 10 | F9: 620 | G9: 0 | H9: Delivered | I9: Neha Kulkarni | J9: =E9*F9*(1-G9/100)
A10: 10141 | B10: 45970 | C10: 0008 | D10: 108 | E10: 65 | F10: 290 | G10: 5 | H10: Delivered | I10: Neha Kulkarni | J10: =E10*F10*(1-G10/100)
A11: 10142 | B11: 45970 | C11: 0015 | D11: 104 | E11: 60 | F11: 620 | G11: 5 | H11: Delivered | I11: Farah Khan | J11: =E11*F11*(1-G11/100)
A12: 10142 | B12: 45970 | C12: 0015 | D12: 108 | E12: 60 | F12: 290 | G12: 5 | H12: Delivered | I12: Farah Khan | J12: =E12*F12*(1-G12/100)
A13: 10143 | B13: 45972 | C13: 0007 | D13: 101 | E13: 55 | F13: 430 | G13: 12 | H13: Delivered | I13: Farah Khan | J13: =E13*F13*(1-G13/100)
... A27: 10149 | B27: 45979 | C27: 0004 | D27: 105 | E27: 15 | F27: 1400 | G27: 12 | H27: Delivered | I27: Rahul Mehta | J27: =E27*F27*(1-G27/100)
A28: 10150 | B28: 45980 | C28: 0022 | D28: 103 | E28: 70 | F28: 115 | G28: 0 | H28: Delivered | J28: =E28*F28*(1-G28/100)
A29: 10151 | B29: 45983 | C29: 0011 | D29: 102 | E29: 35 | F29: 750 | G29: 5 | H29: Delivered | I29: Rahul Mehta | J29: =E29*F29*(1-G29/100)
A30: 10151 | B30: 45983 | C30: 0011 | D30: 105 | E30: 40 | F30: 1400 | G30: 12 | H30: Delivered | I30: Rahul Mehta | J30: =E30*F30*(1-G30/100)
A31: 10152 | B31: 45983 | C31: 0014 | D31: 108 | E31: 45 | F31: 290 | G31: 5 | H31: Delivered | I31: Farah Khan | J31: =E31*F31*(1-G31/100)
A32: 10153 | B32: 45984 | C32: 0017 | D32: 103 | E32: 25 | F32: 115 | G32: 5 | H32: Delivered | J32: =E32*F32*(1-G32/100)
A33: 10154 | B33: 45986 | C33: 0015 | D33: 101 | E33: 25 | F33: 430 | G33: 5 | H33: Delivered | I33: Farah Khan | J33: =E33*F33*(1-G33/100)
A34: 10155 | B34: 45987 | C34: 0003 | D34: 107 | E34: 10 | F34: 380 | G34: 5 | H34: Delivered | I34: Farah Khan | J34: =E34*F34*(1-G34/100)
A35: 10156 | B35: 45987 | C35: 0005 | D35: 101 | E35: 15 | F35: 430 | G35: 0 | H35: Delivered | I35: Rahul Mehta | J35: =E35*F35*(1-G35/100)
A36: 10157 | B36: 45989 | C36: 0018 | D36: 101 | E36: 40 | F36: 430 | G36: 0 | H36: Delivered | I36: Rahul Mehta | J36: =E36*F36*(1-G36/100)

Sheet Dec
A1: order_id | B1: order_date | C1: customer_code | D1: product_id | E1: quantity | F1: unit_price | G1: discount_pct | H1: status | I1: sales_rep | J1: net_revenue
A2: 10158 | B2: 45992 | C2: 0023 | D2: 103 | E2: 5 | F2: 115 | G2: 0 | H2: Delivered | I2: Farah Khan | J2: =E2*F2*(1-G2/100)
A3: 10158 | B3: 45992 | C3: 0023 | D3: 104 | E3: 40 | F3: 620 | G3: 0 | H3: Delivered | I3: Farah Khan | J3: =E3*F3*(1-G3/100)
A4: 10159 | B4: 45992 | C4: 0024 | D4: 101 | E4: 35 | F4: 430 | G4: 10 | H4: Delivered | I4: Rahul Mehta | J4: =E4*F4*(1-G4/100)
A5: 10159 | B5: 45992 | C5: 0024 | D5: 102 | E5: 35 | F5: 750 | G5: 5 | H5: Delivered | I5: Rahul Mehta | J5: =E5*F5*(1-G5/100)
A6: 10159 | B6: 45992 | C6: 0024 | D6: 108 | E6: 30 | F6: 290 | G6: 8 | H6: Delivered | I6: Rahul Mehta | J6: =E6*F6*(1-G6/100)
A7: 10160 | B7: 45995 | C7: 0007 | D7: 101 | E7: 15 | F7: 430 | G7: 12 | H7: Delivered | I7: Farah Khan | J7: =E7*F7*(1-G7/100)
A8: 10160 | B8: 45995 | C8: 0007 | D8: 108 | E8: 15 | F8: 290 | G8: 5 | H8: Delivered | I8: Farah Khan | J8: =E8*F8*(1-G8/100)
A9: 10161 | B9: 45996 | C9: 0001 | D9: 103 | E9: 25 | F9: 115 | G9: 0 | H9: Delivered | I9: Neha Kulkarni | J9: =E9*F9*(1-G9/100)
A10: 10161 | B10: 45996 | C10: 0001 | D10: 107 | E10: 30 | F10: 380 | G10: 5 | H10: Delivered | I10: Neha Kulkarni | J10: =E10*F10*(1-G10/100)
A11: 10162 | B11: 45999 | C11: 0007 | D11: 101 | E11: 35 | F11: 430 | G11: 5 | H11: Delivered | J11: =E11*F11*(1-G11/100)
A12: 10162 | B12: 45999 | C12: 0007 | D12: 105 | E12: 40 | F12: 1400 | G12: 8 | H12: Delivered | J12: =E12*F12*(1-G12/100)
A13: 10163 | B13: 46001 | C13: 0004 | D13: 108 | E13: 15 | F13: 290 | G13: 12 | H13: Delivered | I13: Rahul Mehta | J13: =E13*F13*(1-G13/100)
A14: 10164 | B14: 46001 | C14: 0019 | D14: 101 | E14: 10 | F14: 430 | G14: 10 | H14: Delivered | I14: Farah Khan | J14: =E14*F14*(1-G14/100)
A15: 10165 | B15: 46003 | C15: 0024 | D15: 102 | E15: 15 | F15: 750 | G15: 12 | H15: Delivered | J15: =E15*F15*(1-G15/100)
A16: 10165 | B16: 46003 | C16: 0024 | D16: 108 | E16: 35 | F16: 290 | G16: 10 | H16: Delivered | J16: =E16*F16*(1-G16/100)
A17: 10166 | B17: 46004 | C17: 0023 | D17: 101 | E17: 10 | F17: 430 | G17: 0 | H17: Delivered | I17: Farah Khan | J17: =E17*F17*(1-G17/100)
A18: 10166 | B18: 46004 | C18: 0023 | D18: 104 | E18: 50 | F18: 620 | G18: 0 | H18: Delivered | I18: Farah Khan | J18: =E18*F18*(1-G18/100)
A19: 10167 | B19: 46005 | C19: 0011 | D19: 101 | E19: 35 | F19: 430 | G19: 10 | H19: Delivered | I19: Rahul Mehta | J19: =E19*F19*(1-G19/100)
A20: 10167 | B20: 46005 | C20: 0011 | D20: 108 | E20: 20 | F20: 290 | G20: 10 | H20: Delivered | I20: Rahul Mehta | J20: =E20*F20*(1-G20/100)
A21: 10168 | B21: 46007 | C21: 0005 | D21: 101 | E21: 35 | F21: 430 | G21: 0 | H21: Delivered | I21: Rahul Mehta | J21: =E21*F21*(1-G21/100)
A22: 10168 | B22: 46007 | C22: 0005 | D22: 103 | E22: 20 | F22: 115 | G22: 0 | H22: Delivered | I22: Rahul Mehta | J22: =E22*F22*(1-G22/100)
A23: 10169 | B23: 46007 | C23: 0018 | D23: 101 | E23: 25 | F23: 430 | G23: 5 | H23: Delivered | I23: Rahul Mehta | J23: =E23*F23*(1-G23/100)
A24: 10169 | B24: 46007 | C24: 0018 | D24: 104 | E24: 30 | F24: 620 | G24: 0 | H24: Delivered | I24: Rahul Mehta | J24: =E24*F24*(1-G24/100)
A25: 10169 | B25: 46007 | C25: 0018 | D25: 108 | E25: 25 | F25: 290 | G25: 5 | H25: Delivered | I25: Rahul Mehta | J25: =E25*F25*(1-G25/100)
A26: 10170 | B26: 46007 | C26: 0021 | D26: 101 | E26: 35 | F26: 430 | G26: 0 | H26: Delivered | I26: Rahul Mehta | J26: =E26*F26*(1-G26/100)
A27: 10170 | B27: 46007 | C27: 0021 | D27: 104 | E27: 35 | F27: 620 | G27: 0 | H27: Delivered | I27: Rahul Mehta | J27: =E27*F27*(1-G27/100)
A28: 10171 | B28: 46008 | C28: 0014 | D28: 101 | E28: 30 | F28: 430 | G28: 8 | H28: Delivered | I28: Farah Khan | J28: =E28*F28*(1-G28/100)
... A41: 10175 | B41: 46014 | C41: 0017 | D41: 108 | E41: 30 | F41: 290 | G41: 0 | H41: Shipped | I41: Neha Kulkarni | J41: =E41*F41*(1-G41/100)
