Workbook

Sheet Read me
A1: Analyst to Architect — Full-Book Review: Action Register
A2: Content review 25 September 2026: every chapter (1–83) read in full against the 7 review tests. Visual/layout review 27 September 2026: every page of all 85 chapter PDFs (2,455 pages; final versions — Ch 12 reviewed on Draft v4) checked for figures, tables, text, code blocks, maths, structure and print. Findings only: no chapter has been rewritten.
A3: Visual findings have Test = "Visual"; their Where column starts with the PDF page number (page 1 = chapter cover; printed folio = PDF page − 1). A snapshot of every High and Medium visual finding is in Visual-Review.zip, named <Finding ID>_p<page>.png.
A5: How to use this workbook
A6: 1. "Register" lists every finding in book order. Filter by Part, Chapter, Test or Severity.
A7: 2. Your decision goes in the yellow "Decision" column (Approve / Modify / Reject / Defer). Notes go in "Your notes".
A8: 3. "Summary" counts findings per chapter and your decisions so far; it updates as you fill in decisions.
A9: 4. "Themes" lists the problems that repeat across the book, so one decision can cover many rows.
A11: Severity
A12: High = a beginner gets stuck, is misled, or gets a wrong number or broken code.
A13: Medium = slows or confuses the reader; the book resolves it later.
A14: Low = polish, wording, small inconsistencies.
... A21: Not verified here: live web prices/salaries (Ch 8, 54, 65), legal claims (Ch 64), VBA/DAX/Excel behaviour needing Excel or Power BI, and outputs needing companion data files not available to the reviewers. Each is flagged in its row.

Sheet Summary
A1: Part | B1: Chapter | C1: Title | D1: Findings | E1: High | F1: Medium | G1: Low | H1: Visual | I1: Decided | J1: Approved
A2: 0–I | B2: All | C2: Parts 0–I cross-part (sequence) | D2: =COUNTIFS(Register!$B$2:$B$3759,A2,Register!$C$2:$C$3759,B2) -> 2 | E2: =COUNTIFS(Register!$B$2:$B$3759,A2,Register!$C$2:$C$3759,B2,Register!$H$2:$H$3759,"High") -> 1 | F2: =COUNTIFS(Register!$B$2:$B$3759,A2,Register!$C$2:$C$3759,B2,Register!$H$2:$H$3759,"Medium") -> 1 | G2: =COUNTIFS(Register!$B$2:$B$3759,A2,Register!$C$2:$C$3759,B2,Register!$H$2:$H$3759,"Low") -> 0 | H2: =COUNTIFS(Register!$B$2:$B$3759,A2,Register!$C$2:$C$3759,B2,Register!$G$2:$G$3759,"Visual") -> 0 | I2: =COUNTIFS(Register!$B$2:$B$3759,A2,Register!$C$2:$C$3759,B2,Register!$J$2:$J$3759,"<>") -> 0 | J2: =COUNTIFS(Register!$B$2:$B$3759,A2,Register!$C$2:$C$3759,B2,Register!$J$2:$J$3759,"Approve") -> 0
A3: 0 | B3: 1 | C3: What Is Data | D3: =COUNTIFS(Register!$B$2:$B$3759,A3,Register!$C$2:$C$3759,B3) -> 20 | E3: =COUNTIFS(Register!$B$2:$B$3759,A3,Register!$C$2:$C$3759,B3,Register!$H$2:$H$3759,"High") -> 3 | F3: =COUNTIFS(Register!$B$2:$B$3759,A3,Register!$C$2:$C$3759,B3,Register!$H$2:$H$3759,"Medium") -> 7 | G3: =COUNTIFS(Register!$B$2:$B$3759,A3,Register!$C$2:$C$3759,B3,Register!$H$2:$H$3759,"Low") -> 10 | H3: =COUNTIFS(Register!$B$2:$B$3759,A3,Register!$C$2:$C$3759,B3,Register!$G$2:$G$3759,"Visual") -> 15 | I3: =COUNTIFS(Register!$B$2:$B$3759,A3,Register!$C$2:$C$3759,B3,Register!$J$2:$J$3759,"<>") -> 0 | J3: =COUNTIFS(Register!$B$2:$B$3759,A3,Register!$C$2:$C$3759,B3,Register!$J$2:$J$3759,"Approve") -> 0
A4: 0 | B4: 2 | C4: How Computers Store Move Protect Data | D4: =COUNTIFS(Register!$B$2:$B$3759,A4,Register!$C$2:$C$3759,B4) -> 17 | E4: =COUNTIFS(Register!$B$2:$B$3759,A4,Register!$C$2:$C$3759,B4,Register!$H$2:$H$3759,"High") -> 0 | F4: =COUNTIFS(Register!$B$2:$B$3759,A4,Register!$C$2:$C$3759,B4,Register!$H$2:$H$3759,"Medium") -> 10 | G4: =COUNTIFS(Register!$B$2:$B$3759,A4,Register!$C$2:$C$3759,B4,Register!$H$2:$H$3759,"Low") -> 7 | H4: =COUNTIFS(Register!$B$2:$B$3759,A4,Register!$C$2:$C$3759,B4,Register!$G$2:$G$3759,"Visual") -> 14 | I4: =COUNTIFS(Register!$B$2:$B$3759,A4,Register!$C$2:$C$3759,B4,Register!$J$2:$J$3759,"<>") -> 0 | J4: =COUNTIFS(Register!$B$2:$B$3759,A4,Register!$C$2:$C$3759,B4,Register!$J$2:$J$3759,"Approve") -> 0
A5: 0 | B5: 3 | C5: How a Business Runs on Data | D5: =COUNTIFS(Register!$B$2:$B$3759,A5,Register!$C$2:$C$3759,B5) -> 15 | E5: =COUNTIFS(Register!$B$2:$B$3759,A5,Register!$C$2:$C$3759,B5,Register!$H$2:$H$3759,"High") -> 2 | F5: =COUNTIFS(Register!$B$2:$B$3759,A5,Register!$C$2:$C$3759,B5,Register!$H$2:$H$3759,"Medium") -> 7 | G5: =COUNTIFS(Register!$B$2:$B$3759,A5,Register!$C$2:$C$3759,B5,Register!$H$2:$H$3759,"Low") -> 6 | H5: =COUNTIFS(Register!$B$2:$B$3759,A5,Register!$C$2:$C$3759,B5,Register!$G$2:$G$3759,"Visual") -> 15 | I5: =COUNTIFS(Register!$B$2:$B$3759,A5,Register!$C$2:$C$3759,B5,Register!$J$2:$J$3759,"<>") -> 0 | J5: =COUNTIFS(Register!$B$2:$B$3759,A5,Register!$C$2:$C$3759,B5,Register!$J$2:$J$3759,"Approve") -> 0
A6: 0 | B6: 4 | C6: Numbers Without Fear | D6: =COUNTIFS(Register!$B$2:$B$3759,A6,Register!$C$2:$C$3759,B6) -> 18 | E6: =COUNTIFS(Register!$B$2:$B$3759,A6,Register!$C$2:$C$3759,B6,Register!$H$2:$H$3759,"High") -> 1 | F6: =COUNTIFS(Register!$B$2:$B$3759,A6,Register!$C$2:$C$3759,B6,Register!$H$2:$H$3759,"Medium") -> 10 | G6: =COUNTIFS(Register!$B$2:$B$3759,A6,Register!$C$2:$C$3759,B6,Register!$H$2:$H$3759,"Low") -> 7 | H6: =COUNTIFS(Register!$B$2:$B$3759,A6,Register!$C$2:$C$3759,B6,Register!$G$2:$G$3759,"Visual") -> 15 | I6: =COUNTIFS(Register!$B$2:$B$3759,A6,Register!$C$2:$C$3759,B6,Register!$J$2:$J$3759,"<>") -> 0 | J6: =COUNTIFS(Register!$B$2:$B$3759,A6,Register!$C$2:$C$3759,B6,Register!$J$2:$J$3759,"Approve") -> 0
A7: 0 | B7: 5 | C7: Thinking Like an Analyst | D7: =COUNTIFS(Register!$B$2:$B$3759,A7,Register!$C$2:$C$3759,B7) -> 14 | E7: =COUNTIFS(Register!$B$2:$B$3759,A7,Register!$C$2:$C$3759,B7,Register!$H$2:$H$3759,"High") -> 1 | F7: =COUNTIFS(Register!$B$2:$B$3759,A7,Register!$C$2:$C$3759,B7,Register!$H$2:$H$3759,"Medium") -> 8 | G7: =COUNTIFS(Register!$B$2:$B$3759,A7,Register!$C$2:$C$3759,B7,Register!$H$2:$H$3759,"Low") -> 5 | H7: =COUNTIFS(Register!$B$2:$B$3759,A7,Register!$C$2:$C$3759,B7,Register!$G$2:$G$3759,"Visual") -> 14 | I7: =COUNTIFS(Register!$B$2:$B$3759,A7,Register!$C$2:$C$3759,B7,Register!$J$2:$J$3759,"<>") -> 0 | J7: =COUNTIFS(Register!$B$2:$B$3759,A7,Register!$C$2:$C$3759,B7,Register!$J$2:$J$3759,"Approve") -> 0
A8: 0 | B8: 6 | C8: Setting Up to Learn | D8: =COUNTIFS(Register!$B$2:$B$3759,A8,Register!$C$2:$C$3759,B8) -> 20 | E8: =COUNTIFS(Register!$B$2:$B$3759,A8,Register!$C$2:$C$3759,B8,Register!$H$2:$H$3759,"High") -> 3 | F8: =COUNTIFS(Register!$B$2:$B$3759,A8,Register!$C$2:$C$3759,B8,Register!$H$2:$H$3759,"Medium") -> 8 | G8: =COUNTIFS(Register!$B$2:$B$3759,A8,Register!$C$2:$C$3759,B8,Register!$H$2:$H$3759,"Low") -> 7 | H8: =COUNTIFS(Register!$B$2:$B$3759,A8,Register!$C$2:$C$3759,B8,Register!$G$2:$G$3759,"Visual") -> 13 | I8: =COUNTIFS(Register!$B$2:$B$3759,A8,Register!$C$2:$C$3759,B8,Register!$J$2:$J$3759,"<>") -> 0 | J8: =COUNTIFS(Register!$B$2:$B$3759,A8,Register!$C$2:$C$3759,B8,Register!$J$2:$J$3759,"Approve") -> 0
A9: I | B9: 7 | C9: The Data Landscape | D9: =COUNTIFS(Register!$B$2:$B$3759,A9,Register!$C$2:$C$3759,B9) -> 18 | E9: =COUNTIFS(Register!$B$2:$B$3759,A9,Register!$C$2:$C$3759,B9,Register!$H$2:$H$3759,"High") -> 2 | F9: =COUNTIFS(Register!$B$2:$B$3759,A9,Register!$C$2:$C$3759,B9,Register!$H$2:$H$3759,"Medium") -> 11 | G9: =COUNTIFS(Register!$B$2:$B$3759,A9,Register!$C$2:$C$3759,B9,Register!$H$2:$H$3759,"Low") -> 5 | H9: =COUNTIFS(Register!$B$2:$B$3759,A9,Register!$C$2:$C$3759,B9,Register!$G$2:$G$3759,"Visual") -> 15 | I9: =COUNTIFS(Register!$B$2:$B$3759,A9,Register!$C$2:$C$3759,B9,Register!$J$2:$J$3759,"<>") -> 0 | J9: =COUNTIFS(Register!$B$2:$B$3759,A9,Register!$C$2:$C$3759,B9,Register!$J$2:$J$3759,"Approve") -> 0
A10: I | B10: 8 | C10: The Career Tree How Skills Unlock Roles | D10: =COUNTIFS(Register!$B$2:$B$3759,A10,Register!$C$2:$C$3759,B10) -> 19 | E10: =COUNTIFS(Register!$B$2:$B$3759,A10,Register!$C$2:$C$3759,B10,Register!$H$2:$H$3759,"High") -> 3 | F10: =COUNTIFS(Register!$B$2:$B$3759,A10,Register!$C$2:$C$3759,B10,Register!$H$2:$H$3759,"Medium") -> 10 | G10: =COUNTIFS(Register!$B$2:$B$3759,A10,Register!$C$2:$C$3759,B10,Register!$H$2:$H$3759,"Low") -> 6 | H10: =COUNTIFS(Register!$B$2:$B$3759,A10,Register!$C$2:$C$3759,B10,Register!$G$2:$G$3759,"Visual") -> 14 | I10: =COUNTIFS(Register!$B$2:$B$3759,A10,Register!$C$2:$C$3759,B10,Register!$J$2:$J$3759,"<>") -> 0 | J10: =COUNTIFS(Register!$B$2:$B$3759,A10,Register!$C$2:$C$3759,B10,Register!$J$2:$J$3759,"Approve") -> 0
A11: I | B11: 9 | C11: How Expertise Actually Forms | D11: =COUNTIFS(Register!$B$2:$B$3759,A11,Register!$C$2:$C$3759,B11) -> 14 | E11: =COUNTIFS(Register!$B$2:$B$3759,A11,Register!$C$2:$C$3759,B11,Register!$H$2:$H$3759,"High") -> 0 | F11: =COUNTIFS(Register!$B$2:$B$3759,A11,Register!$C$2:$C$3759,B11,Register!$H$2:$H$3759,"Medium") -> 9 | G11: =COUNTIFS(Register!$B$2:$B$3759,A11,Register!$C$2:$C$3759,B11,Register!$H$2:$H$3759,"Low") -> 5 | H11: =COUNTIFS(Register!$B$2:$B$3759,A11,Register!$C$2:$C$3759,B11,Register!$G$2:$G$3759,"Visual") -> 13 | I11: =COUNTIFS(Register!$B$2:$B$3759,A11,Register!$C$2:$C$3759,B11,Register!$J$2:$J$3759,"<>") -> 0 | J11: =COUNTIFS(Register!$B$2:$B$3759,A11,Register!$C$2:$C$3759,B11,Register!$J$2:$J$3759,"Approve") -> 0
A12: II | B12: 10 | C12: Spreadsheet Fundamentals Excel and Google Sheets | D12: =COUNTIFS(Register!$B$2:$B$3759,A12,Register!$C$2:$C$3759,B12) -> 52 | E12: =COUNTIFS(Register!$B$2:$B$3759,A12,Register!$C$2:$C$3759,B12,Register!$H$2:$H$3759,"High") -> 4 | F12: =COUNTIFS(Register!$B$2:$B$3759,A12,Register!$C$2:$C$3759,B12,Register!$H$2:$H$3759,"Medium") -> 25 | G12: =COUNTIFS(Register!$B$2:$B$3759,A12,Register!$C$2:$C$3759,B12,Register!$H$2:$H$3759,"Low") -> 23 | H12: =COUNTIFS(Register!$B$2:$B$3759,A12,Register!$C$2:$C$3759,B12,Register!$G$2:$G$3759,"Visual") -> 19 | I12: =COUNTIFS(Register!$B$2:$B$3759,A12,Register!$C$2:$C$3759,B12,Register!$J$2:$J$3759,"<>") -> 0 | J12: =COUNTIFS(Register!$B$2:$B$3759,A12,Register!$C$2:$C$3759,B12,Register!$J$2:$J$3759,"Approve") -> 0
A13: II | B13: 11 | C13: The Spreadsheet, Mastered: Excel & Google Sheets | D13: =COUNTIFS(Register!$B$2:$B$3759,A13,Register!$C$2:$C$3759,B13) -> 60 | E13: =COUNTIFS(Register!$B$2:$B$3759,A13,Register!$C$2:$C$3759,B13,Register!$H$2:$H$3759,"High") -> 12 | F13: =COUNTIFS(Register!$B$2:$B$3759,A13,Register!$C$2:$C$3759,B13,Register!$H$2:$H$3759,"Medium") -> 30 | G13: =COUNTIFS(Register!$B$2:$B$3759,A13,Register!$C$2:$C$3759,B13,Register!$H$2:$H$3759,"Low") -> 18 | H13: =COUNTIFS(Register!$B$2:$B$3759,A13,Register!$C$2:$C$3759,B13,Register!$G$2:$G$3759,"Visual") -> 26 | I13: =COUNTIFS(Register!$B$2:$B$3759,A13,Register!$C$2:$C$3759,B13,Register!$J$2:$J$3759,"<>") -> 0 | J13: =COUNTIFS(Register!$B$2:$B$3759,A13,Register!$C$2:$C$3759,B13,Register!$J$2:$J$3759,"Approve") -> 0
... A87: Closing | B87: 83 | C87: The Long Game (Closing) | D87: =COUNTIFS(Register!$B$2:$B$3759,A87,Register!$C$2:$C$3759,B87) -> 17 | E87: =COUNTIFS(Register!$B$2:$B$3759,A87,Register!$C$2:$C$3759,B87,Register!$H$2:$H$3759,"High") -> 3 | F87: =COUNTIFS(Register!$B$2:$B$3759,A87,Register!$C$2:$C$3759,B87,Register!$H$2:$H$3759,"Medium") -> 5 | G87: =COUNTIFS(Register!$B$2:$B$3759,A87,Register!$C$2:$C$3759,B87,Register!$H$2:$H$3759,"Low") -> 9 | H87: =COUNTIFS(Register!$B$2:$B$3759,A87,Register!$C$2:$C$3759,B87,Register!$G$2:$G$3759,"Visual") -> 11 | I87: =COUNTIFS(Register!$B$2:$B$3759,A87,Register!$C$2:$C$3759,B87,Register!$J$2:$J$3759,"<>") -> 0 | J87: =COUNTIFS(Register!$B$2:$B$3759,A87,Register!$C$2:$C$3759,B87,Register!$J$2:$J$3759,"Approve") -> 0
C88: Total | D88: =SUM(D2:D87) -> 3758 | E88: =SUM(E2:E87) -> 501 | F88: =SUM(F2:F87) -> 1702 | G88: =SUM(G2:G87) -> 1553 | H88: =SUM(H2:H87) -> 1224 | I88: =SUM(I2:I87) -> 0 | J88: =SUM(J2:J87) -> 0

Sheet Themes
A1: # | B1: Theme (repeats across the book) | C1: Where it shows up (examples) | D1: One decision that would cover it
A2: 1 | B2: Code shown before it is taught (sequence rule) | C2: Parts 0–I (S.1); Ch 14–15 pandas; Ch 12 JOIN before §12.10; Ch 17 loops/keyword args before explained; Ch 18 merge/lambda; Ch 28 recursion; Ch 33 recursion before §33.6; Ch 34 pipes in §34.2 | D2: Apply the sequence rule book-wide: every chapter re-ordered so each keyword, function or library appears first in the section that teaches it
A3: 2 | B3: Tools and libraries never installed | C3: scikit-learn (Ch 35–36), scipy (Ch 21), xgboost/lightgbm/optuna (Ch 37), umap/mlxtend (Ch 38), NLTK/gensim/implicit (Ch 41–42), PyTorch CPU build (Ch 43, 53), Dagster web server (Ch 46), Java + Spark, Polars (Ch 48), Kafka (Ch 50), Docker/kubectl/Terraform (Ch 52), FastAPI/uvicorn/MLflow (Ch 56), LLM SDK + API key (Ch 54), psql client (Ch 12, 28, 32), tabulate (Ch 18) | D3: Extend just-in-time setup to every tool: an install cell + one-line first check at the start of the chapter that first uses it
A4: 3 | B4: Big code blocks with many new ideas at once | C4: Ch 17 first REPL blocks; Ch 18 §18.15 125-line script; Ch 29 60-line API client; Ch 36 40-line first scikit-learn block (10 classes); Ch 37 setup blocks (8–13 ideas); Ch 50 Spark/Kafka cells (12–15 ideas); Ch 28 38-line SCD insert | D4: Standard: one new idea per cell, output shown, every line and argument explained; long scripts built in stages
A5: 4 | B5: No by-hand example before the method | C5: Ch 21–22 formulas never written in symbols; Ch 37 linear regression, ridge/lasso, k-NN, forests; Ch 38 hierarchical, DBSCAN, silhouette; Ch 39 every metric; Ch 40 decomposition, ACF; Ch 41 TF-IDF, word2vec; Ch 42 matrix factorization; Ch 43/53 backprop | D5: Standard ladder for every method: plain idea → tiny by-hand example → spreadsheet (where sensible) → code
A6: 5 | B6: Foundations the book never teaches | C6: Logarithms (Ch 31, 35, 36), chain rule (Ch 43, 53), Python classes/decorators/type hints (Ch 29), JavaScript/TypeScript/HTML (Ch 19), YAML/Jinja (Ch 26, 32), regular expressions (Ch 14), JSON in Python (Ch 18), autocorrelation (Ch 40), topological sort (Ch 77), isolation levels (Ch 71) | D6: Add short primers ("Logs in ten minutes", "Classes in 20 minutes", "YAML in ten minutes", etc.) where first needed, or remove the dependency
A7: 6 | B7: Hidden companion code and black-box outputs | C7: Ch 14 cleaning pipeline built by a script; Ch 46 ingest.py; Ch 51 scoring rule; Ch 55 VectorIndex/SupportAssistant; Ch 57 registry/meter/cache; Ch 58 run() pipeline; Ch 27 outputs with no code | D7: Rule: every output in the text comes from code on the page (or an explicitly shown companion file walkthrough)
A8: 7 | B8: Printed outputs that are errors or cannot come from the code | C8: Ch 18 TypeError/NameError/KeyError outputs; Ch 51 seven NameError cells; Ch 46 mock CRM shut down early; Ch 17 REPL output missing 22; Ch 42 Ex 9 ValueError; Ch 54 Answer 7 crash; Ch 78 retry NameError | D8: Re-run every chapter top to bottom on the stated versions before print; regenerate outputs
A9: 8 | B9: Wrong chapter/section cross-references | C9: "Chapter 19" for regression (Ch 30, 31, 53, 59); "Chapter 38" for evaluation/leakage (Ch 53–56, 59); "Chapter 52" for MLOps (Ch 36, 38, 39, 40); "Chapter 23" for semantic layer (Ch 60–64); "Chapter 76" which does not exist (12 chapters); "Chapter 74" for banks (Ch 57, 58); many more in each file | D9: One cross-reference pass after all moves, using a generated chapter/section index
A10: 9 | B10: Part VIII pointers and numbering | C10: "Learn it in" pointers placeholder/self-referential (Ch 72 → itself, Ch 73 "to confirm", Ch 75/78/82 point to other banks); 72A/76A/76B numbering and no Ch 76; questions on topics never taught (Monty Hall, RICE, INVEST, Gherkin, closures, decorators, MVCC); no difficulty labels; "Passes" tier describes red flags | D10: Renumber Part VIII (proposal in Ch 72A review); fixed question codes (SQL-001…); every question points to a teaching section; untaught questions removed or taught
A11: 10 | B11: Riverstone facts that disagree across chapters | C11: Warehouse DuckDB (Part V) vs "Postgres + Delta" (Part VII); hourly rate ₹300 vs ₹1,200 (Ch 20, 58, 63, 66, 80); exchange rate ₹83/₹87/₹88; Meera timeline (Ch 1 vs Ch 83); Farah story (Ch 8/9 vs Ch 68); sensor dataset (Ch 40 vs 48); lead vs churn AUCs (Ch 74, 76A, 82 vs Ch 36–39); invoicing manual vs automatic (Ch 25/76B vs Ch 3); flash time 06:00/06:30/07:30 | D11: A single "Riverstone fact sheet" (people, timeline, systems, rates, datasets) that every chapter is checked against
A12: 11 | B12: Drafting and authoring leftovers | C12: "(In the finished book… Appendix G)" (59); "first edition"/"draft" (Ch 6, 8, 9, 48); "this chat doesn't have…" (Ch 70–74, 77–80, 82); "blueprint" (Ch 48, 78, 82); coordinator renumbering notes (72A, 76A); AI-authoring note (Ch 67); build scripts named as reader files (Ch 8, 9, 14, 15, 36, 40) | D12: One polish pass with a search list; can be done now
A13: 12 | B13: Time needed estimates too low | C13: Ch 11 (25–30 → 35–45 h), Ch 12 (19–23 → 27–35 h), Ch 28, 35, 36 (8–12 → 14–18 h), 39, 40, 52 (12–16 → 20–26 h) | D13: Re-measure after fixes; recompute Ch 6, Ch 9 and Closing tables from one source
... A27: 26 | B27: Integrity of examples and advice | C27: Ch 54 prompting numbers come from a mock but are called "real"; Ch 81 advises telling other people's stories in first person; Ch 76A/81 present textbook projects as the candidate's own work; Ch 44 "value at risk" called revenue | D27: Label simulated results as simulated; interview advice uses only the reader's own work

Sheet Register
A1: # | B1: Part | C1: Chapter | D1: Finding ID | E1: Where | F1: Issue | G1: Test | H1: Severity | I1: Change needed | J1: Decision | K1: Your notes
A2: 1 | B2: 0–I | C2: All | D2: S.1 | E2: Parts 0, I | F2: Code shown before it is taught (table above). "You don't need to read this yet" labels don't fix it. | G2: Sequence | H2: High | I2: See fix-instructions-part-0-and-I.md (fix dependency: Needs map)
A3: 2 | B3: 0–I | C3: All | D3: 0.7 | E3: All chapters | F3: Heavy forward references (Ch 12–78) in nearly every section. | G3: Flow | H3: Medium | I3: See fix-instructions-part-0-and-I.md (fix dependency: Needs map)
A4: 3 | B4: 0 | C4: 1 | D4: 0.8 | E4: Ch 1–6 | F4: Two datasets used without introduction: mini database (Q1 2026, 12 orders) vs one-year database (2025, 173 orders); March = ₹31,800 in one chapter, ₹278,008 in another. | G4: Consistency | H4: Medium | I4: See fix-instructions-part-0-and-I.md (fix dependency: Independent)
A5: 4 | B5: 0 | C5: 1 | D5: 0.9 | E5: Ch 1–5 | F5: Fast-growing cast (Meera, Anita, Vikram, Neha, Rahul, Farah, Suresh, Imran, Rakesh, Kavya); no cast list or company fact sheet. | G5: First-time reader | H5: Low | I5: See fix-instructions-part-0-and-I.md (fix dependency: Independent)
A6: 5 | B6: 0 | C6: 1 | D6: 0.11 | E6: Ch 1 §1.6, Fig 1.3 | F6: "Each level allows everything the level above it allows" reads backwards. | G6: First-time reader | H6: Low | I6: See fix-instructions-part-0-and-I.md (fix dependency: Independent)
A7: 6 | B7: 0 | C7: 1 | D7: 0.12 | E7: Ch 1 §1.6 ex. 2 | F7: Kelvin conversion is unnecessary physics for the point. | G7: Load | H7: Low | I7: See fix-instructions-part-0-and-I.md (fix dependency: Independent)
A8: 7 | B8: 0 | C8: 1 | D8: 0.15 | E8: Ch 1–6 answers | F8: "(In the finished book these move to Appendix G.)" production note in every chapter. | G8: Polish | H8: Low | I8: See fix-instructions-part-0-and-I.md (fix dependency: Independent)
A9: 8 | B9: 0 | C9: 1 | D9: V1.1 | E9: p. 17 · Code block: Kavya's three days (project) | F9: All 8 data rows and the header wrap: "…│ Station" / "stall │ No", "…│ shop" / "│ necessary". The dashed rule also breaks onto a second line. The table readers are asked to copy no longer reads as a table. | G9: Visual | H9: High | I9: Drop a column or shorten values ("Station stall" → "Stall"), or reduce the block to 7 pt with no-wrap. Alternatively set it as a normal table like the column spec above it.
A10: 9 | B10: 0 | C10: 1 | D10: V1.2 | E10: p. 6 · Figure 1.2 (receipt → table) | F10: Receipt and table text is 4.9–5.4 pt. The table's column headers and cells, the chapter's first data table, are unreadable in print. | G10: Visual | H10: High | I10: Redraw at ≥ 7 pt. Stack the receipt above the table so each gets full width.
A11: 10 | B11: 0 | C11: 1 | D11: V1.3 | E11: p. 11 · Figure 1.4 (structured / semi-structured / unstructured) | F11: All three panels are 4.9–5.2 pt, including the JSON and email text the prose tells readers to look at ("the middle panel… every value has a name"). | G11: Visual | H11: High | I11: Enlarge to ≥ 7 pt, stacked vertically if needed, or show fewer lines per panel.
A12: 11 | B12: 0 | C12: 1 | D12: V1.4 | E12: p. 5 · Figure 1.1 (data → insight staircase) | F12: Box text 5.1–5.6 pt; the bottom note "Each step up needs more context…" is 5.1 pt. | G12: Visual | H12: Medium | I12: Scale up to ≥ 7 pt, or drop the per-box detail lines.
A13: 12 | B13: 0 | C13: 1 | D13: V1.5 | E13: p. 9 · Figure 1.3 (levels of measurement) | F13: Descriptions and "e.g." lines are 5.3–5.8 pt; right-hand pills are about 6 pt. | G13: Visual | H13: Medium | I13: Increase to ≥ 7 pt; the figure has spare height.
... A3759: 3758 | B3759: Closing | C3759: 83 | D3759: V83.11 | E3759: p. 6 · Figure 83.2 x-axis | F3759: The ticks run 0, 25, 50, 75, 100, 125, 156. The last tick breaks the interval. | G3759: Visual | H3759: Low | I3759: Use 0–150 in steps of 25 with a "year 3 (156)" annotation, or ticks at 0/52/104/156 (years).
