Workbook

Sheet Tracker
A1: Riverstone Supplies — Monthly sales tracker, 2025
A2: Net revenue = quantity × unit price × (1 − discount %). Cancelled orders excluded. Source: ERP export.
A4: month | B4: target | C4: orders | D4: net_revenue | E4: pct_of_target | F4: vs_prev_month | G4: status
A5: =Targets!A2 | B5: =Targets!B2 | C5: =SUMIFS(Data!$L$2:$L$331,Data!$K$2:$K$331,A5,Data!$H$2:$H$331,"<>Cancelled") | D5: =SUMIFS(Data!$J$2:$J$331,Data!$B$2:$B$331,">="&A5,Data!$B$2:$B$331,"<="&EOMONTH(A5,0),Data!$H$2:$H$331,"<>Cancelled") | E5: =D5/B5 | G5: =IF(D5>=B5,"On target","Below target")
A6: =Targets!A3 | B6: =Targets!B3 | C6: =SUMIFS(Data!$L$2:$L$331,Data!$K$2:$K$331,A6,Data!$H$2:$H$331,"<>Cancelled") | D6: =SUMIFS(Data!$J$2:$J$331,Data!$B$2:$B$331,">="&A6,Data!$B$2:$B$331,"<="&EOMONTH(A6,0),Data!$H$2:$H$331,"<>Cancelled") | E6: =D6/B6 | F6: =D6/D5-1 | G6: =IF(D6>=B6,"On target","Below target")
A7: =Targets!A4 | B7: =Targets!B4 | C7: =SUMIFS(Data!$L$2:$L$331,Data!$K$2:$K$331,A7,Data!$H$2:$H$331,"<>Cancelled") | D7: =SUMIFS(Data!$J$2:$J$331,Data!$B$2:$B$331,">="&A7,Data!$B$2:$B$331,"<="&EOMONTH(A7,0),Data!$H$2:$H$331,"<>Cancelled") | E7: =D7/B7 | F7: =D7/D6-1 | G7: =IF(D7>=B7,"On target","Below target")
A8: =Targets!A5 | B8: =Targets!B5 | C8: =SUMIFS(Data!$L$2:$L$331,Data!$K$2:$K$331,A8,Data!$H$2:$H$331,"<>Cancelled") | D8: =SUMIFS(Data!$J$2:$J$331,Data!$B$2:$B$331,">="&A8,Data!$B$2:$B$331,"<="&EOMONTH(A8,0),Data!$H$2:$H$331,"<>Cancelled") | E8: =D8/B8 | F8: =D8/D7-1 | G8: =IF(D8>=B8,"On target","Below target")
A9: =Targets!A6 | B9: =Targets!B6 | C9: =SUMIFS(Data!$L$2:$L$331,Data!$K$2:$K$331,A9,Data!$H$2:$H$331,"<>Cancelled") | D9: =SUMIFS(Data!$J$2:$J$331,Data!$B$2:$B$331,">="&A9,Data!$B$2:$B$331,"<="&EOMONTH(A9,0),Data!$H$2:$H$331,"<>Cancelled") | E9: =D9/B9 | F9: =D9/D8-1 | G9: =IF(D9>=B9,"On target","Below target")
A10: =Targets!A7 | B10: =Targets!B7 | C10: =SUMIFS(Data!$L$2:$L$331,Data!$K$2:$K$331,A10,Data!$H$2:$H$331,"<>Cancelled") | D10: =SUMIFS(Data!$J$2:$J$331,Data!$B$2:$B$331,">="&A10,Data!$B$2:$B$331,"<="&EOMONTH(A10,0),Data!$H$2:$H$331,"<>Cancelled") | E10: =D10/B10 | F10: =D10/D9-1 | G10: =IF(D10>=B10,"On target","Below target")
A11: =Targets!A8 | B11: =Targets!B8 | C11: =SUMIFS(Data!$L$2:$L$331,Data!$K$2:$K$331,A11,Data!$H$2:$H$331,"<>Cancelled") | D11: =SUMIFS(Data!$J$2:$J$331,Data!$B$2:$B$331,">="&A11,Data!$B$2:$B$331,"<="&EOMONTH(A11,0),Data!$H$2:$H$331,"<>Cancelled") | E11: =D11/B11 | F11: =D11/D10-1 | G11: =IF(D11>=B11,"On target","Below target")
A12: =Targets!A9 | B12: =Targets!B9 | C12: =SUMIFS(Data!$L$2:$L$331,Data!$K$2:$K$331,A12,Data!$H$2:$H$331,"<>Cancelled") | D12: =SUMIFS(Data!$J$2:$J$331,Data!$B$2:$B$331,">="&A12,Data!$B$2:$B$331,"<="&EOMONTH(A12,0),Data!$H$2:$H$331,"<>Cancelled") | E12: =D12/B12 | F12: =D12/D11-1 | G12: =IF(D12>=B12,"On target","Below target")
A13: =Targets!A10 | B13: =Targets!B10 | C13: =SUMIFS(Data!$L$2:$L$331,Data!$K$2:$K$331,A13,Data!$H$2:$H$331,"<>Cancelled") | D13: =SUMIFS(Data!$J$2:$J$331,Data!$B$2:$B$331,">="&A13,Data!$B$2:$B$331,"<="&EOMONTH(A13,0),Data!$H$2:$H$331,"<>Cancelled") | E13: =D13/B13 | F13: =D13/D12-1 | G13: =IF(D13>=B13,"On target","Below target")
A14: =Targets!A11 | B14: =Targets!B11 | C14: =SUMIFS(Data!$L$2:$L$331,Data!$K$2:$K$331,A14,Data!$H$2:$H$331,"<>Cancelled") | D14: =SUMIFS(Data!$J$2:$J$331,Data!$B$2:$B$331,">="&A14,Data!$B$2:$B$331,"<="&EOMONTH(A14,0),Data!$H$2:$H$331,"<>Cancelled") | E14: =D14/B14 | F14: =D14/D13-1 | G14: =IF(D14>=B14,"On target","Below target")
A15: =Targets!A12 | B15: =Targets!B12 | C15: =SUMIFS(Data!$L$2:$L$331,Data!$K$2:$K$331,A15,Data!$H$2:$H$331,"<>Cancelled") | D15: =SUMIFS(Data!$J$2:$J$331,Data!$B$2:$B$331,">="&A15,Data!$B$2:$B$331,"<="&EOMONTH(A15,0),Data!$H$2:$H$331,"<>Cancelled") | E15: =D15/B15 | F15: =D15/D14-1 | G15: =IF(D15>=B15,"On target","Below target")
A16: =Targets!A13 | B16: =Targets!B13 | C16: =SUMIFS(Data!$L$2:$L$331,Data!$K$2:$K$331,A16,Data!$H$2:$H$331,"<>Cancelled") | D16: =SUMIFS(Data!$J$2:$J$331,Data!$B$2:$B$331,">="&A16,Data!$B$2:$B$331,"<="&EOMONTH(A16,0),Data!$H$2:$H$331,"<>Cancelled") | E16: =D16/B16 | F16: =D16/D15-1 | G16: =IF(D16>=B16,"On target","Below target")
A17: Total | B17: =SUM(B5:B16) | C17: =SUM(C5:C16) | D17: =SUM(D5:D16) | E17: =D17/B17
A19: Check: total net revenue on the Data sheet (non-cancelled) | D19: =SUMIFS(Data!$J$2:$J$331,Data!$H$2:$H$331,"<>Cancelled")
A20: Check: difference (must be 0) | D20: =D17-D19

Sheet Reps
A1: sales_rep | B1: orders | C1: net_revenue | D1: share_of_total | F1: Pick a rep: | G1: Neha Kulkarni
A2: Neha Kulkarni | B2: =SUMIFS(Data!$L$2:$L$331,Data!$I$2:$I$331,A2,Data!$H$2:$H$331,"<>Cancelled") | C2: =SUMIFS(Data!$J$2:$J$331,Data!$I$2:$I$331,A2,Data!$H$2:$H$331,"<>Cancelled") | D2: =C2/$C$6 | F2: Net revenue: | G2: =SUMIFS(Data!$J$2:$J$331,Data!$I$2:$I$331,G1,Data!$H$2:$H$331,"<>Cancelled")
A3: Rahul Mehta | B3: =SUMIFS(Data!$L$2:$L$331,Data!$I$2:$I$331,A3,Data!$H$2:$H$331,"<>Cancelled") | C3: =SUMIFS(Data!$J$2:$J$331,Data!$I$2:$I$331,A3,Data!$H$2:$H$331,"<>Cancelled") | D3: =C3/$C$6
A4: Farah Khan | B4: =SUMIFS(Data!$L$2:$L$331,Data!$I$2:$I$331,A4,Data!$H$2:$H$331,"<>Cancelled") | C4: =SUMIFS(Data!$J$2:$J$331,Data!$I$2:$I$331,A4,Data!$H$2:$H$331,"<>Cancelled") | D4: =C4/$C$6
A5: (no rep) | B5: =SUMIFS(Data!$L$2:$L$331,Data!$I$2:$I$331,"",Data!$H$2:$H$331,"<>Cancelled") | C5: =SUMIFS(Data!$J$2:$J$331,Data!$I$2:$I$331,"",Data!$H$2:$H$331,"<>Cancelled") | D5: =C5/$C$6
A6: Total | B6: =SUM(B2:B5) | C6: =SUM(C2:C5) | D6: =SUM(D2:D5)
A9: segment | B9: orders | C9: net_revenue | D9: share_of_total
A10: Retail | B10: =SUMIFS(Data!$L$2:$L$331,Data!$N$2:$N$331,A10,Data!$H$2:$H$331,"<>Cancelled") | C10: =SUMIFS(Data!$J$2:$J$331,Data!$N$2:$N$331,A10,Data!$H$2:$H$331,"<>Cancelled") | D10: =C10/SUM($C$10:$C$12)
A11: Hospitality | B11: =SUMIFS(Data!$L$2:$L$331,Data!$N$2:$N$331,A11,Data!$H$2:$H$331,"<>Cancelled") | C11: =SUMIFS(Data!$J$2:$J$331,Data!$N$2:$N$331,A11,Data!$H$2:$H$331,"<>Cancelled") | D11: =C11/SUM($C$10:$C$12)
A12: Wholesale | B12: =SUMIFS(Data!$L$2:$L$331,Data!$N$2:$N$331,A12,Data!$H$2:$H$331,"<>Cancelled") | C12: =SUMIFS(Data!$J$2:$J$331,Data!$N$2:$N$331,A12,Data!$H$2:$H$331,"<>Cancelled") | D12: =C12/SUM($C$10:$C$12)

Sheet Data
A1: order_id | B1: order_date | C1: customer_code | D1: product_id | E1: quantity | F1: unit_price | G1: discount_pct | H1: status | I1: sales_rep | J1: net_revenue | K1: month_start | L1: first_line_of_order | M1: customer_name | N1: segment
A2: 10001 | B2: 45659 | C2: 0002 | D2: 108 | E2: 10 | F2: 290 | G2: 0 | H2: Delivered | I2: Neha Kulkarni | J2: =E2*F2*(1-G2/100) | K2: =DATE(YEAR(B2),MONTH(B2),1) | L2: =IF(COUNTIF($A$2:A2,A2)=1,1,0) | M2: =_xlfn.XLOOKUP(C2,Customers!$A$2:$A$25,Customers!$B$2:$B$25,"not found") | N2: =_xlfn.XLOOKUP(C2,Customers!$A$2:$A$25,Customers!$D$2:$D$25,"not found")
A3: 10002 | B3: 45662 | C3: 0003 | D3: 107 | E3: 55 | F3: 380 | G3: 0 | H3: Delivered | I3: Farah Khan | J3: =E3*F3*(1-G3/100) | K3: =DATE(YEAR(B3),MONTH(B3),1) | L3: =IF(COUNTIF($A$2:A3,A3)=1,1,0) | M3: =_xlfn.XLOOKUP(C3,Customers!$A$2:$A$25,Customers!$B$2:$B$25,"not found") | N3: =_xlfn.XLOOKUP(C3,Customers!$A$2:$A$25,Customers!$D$2:$D$25,"not found")
A4: 10003 | B4: 45669 | C4: 0005 | D4: 101 | E4: 25 | F4: 430 | G4: 0 | H4: Delivered | I4: Rahul Mehta | J4: =E4*F4*(1-G4/100) | K4: =DATE(YEAR(B4),MONTH(B4),1) | L4: =IF(COUNTIF($A$2:A4,A4)=1,1,0) | M4: =_xlfn.XLOOKUP(C4,Customers!$A$2:$A$25,Customers!$B$2:$B$25,"not found") | N4: =_xlfn.XLOOKUP(C4,Customers!$A$2:$A$25,Customers!$D$2:$D$25,"not found")
A5: 10003 | B5: 45669 | C5: 0005 | D5: 102 | E5: 45 | F5: 750 | G5: 5 | H5: Delivered | I5: Rahul Mehta | J5: =E5*F5*(1-G5/100) | K5: =DATE(YEAR(B5),MONTH(B5),1) | L5: =IF(COUNTIF($A$2:A5,A5)=1,1,0) | M5: =_xlfn.XLOOKUP(C5,Customers!$A$2:$A$25,Customers!$B$2:$B$25,"not found") | N5: =_xlfn.XLOOKUP(C5,Customers!$A$2:$A$25,Customers!$D$2:$D$25,"not found")
A6: 10003 | B6: 45669 | C6: 0005 | D6: 108 | E6: 10 | F6: 290 | G6: 0 | H6: Delivered | I6: Rahul Mehta | J6: =E6*F6*(1-G6/100) | K6: =DATE(YEAR(B6),MONTH(B6),1) | L6: =IF(COUNTIF($A$2:A6,A6)=1,1,0) | M6: =_xlfn.XLOOKUP(C6,Customers!$A$2:$A$25,Customers!$B$2:$B$25,"not found") | N6: =_xlfn.XLOOKUP(C6,Customers!$A$2:$A$25,Customers!$D$2:$D$25,"not found")
A7: 10004 | B7: 45670 | C7: 0005 | D7: 101 | E7: 40 | F7: 430 | G7: 0 | H7: Delivered | I7: Rahul Mehta | J7: =E7*F7*(1-G7/100) | K7: =DATE(YEAR(B7),MONTH(B7),1) | L7: =IF(COUNTIF($A$2:A7,A7)=1,1,0) | M7: =_xlfn.XLOOKUP(C7,Customers!$A$2:$A$25,Customers!$B$2:$B$25,"not found") | N7: =_xlfn.XLOOKUP(C7,Customers!$A$2:$A$25,Customers!$D$2:$D$25,"not found")
A8: 10004 | B8: 45670 | C8: 0005 | D8: 102 | E8: 15 | F8: 750 | G8: 5 | H8: Delivered | I8: Rahul Mehta | J8: =E8*F8*(1-G8/100) | K8: =DATE(YEAR(B8),MONTH(B8),1) | L8: =IF(COUNTIF($A$2:A8,A8)=1,1,0) | M8: =_xlfn.XLOOKUP(C8,Customers!$A$2:$A$25,Customers!$B$2:$B$25,"not found") | N8: =_xlfn.XLOOKUP(C8,Customers!$A$2:$A$25,Customers!$D$2:$D$25,"not found")
A9: 10005 | B9: 45677 | C9: 0003 | D9: 101 | E9: 15 | F9: 430 | G9: 5 | H9: Delivered | I9: Farah Khan | J9: =E9*F9*(1-G9/100) | K9: =DATE(YEAR(B9),MONTH(B9),1) | L9: =IF(COUNTIF($A$2:A9,A9)=1,1,0) | M9: =_xlfn.XLOOKUP(C9,Customers!$A$2:$A$25,Customers!$B$2:$B$25,"not found") | N9: =_xlfn.XLOOKUP(C9,Customers!$A$2:$A$25,Customers!$D$2:$D$25,"not found")
A10: 10006 | B10: 45678 | C10: 0004 | D10: 102 | E10: 25 | F10: 750 | G10: 5 | H10: Delivered | I10: Rahul Mehta | J10: =E10*F10*(1-G10/100) | K10: =DATE(YEAR(B10),MONTH(B10),1) | L10: =IF(COUNTIF($A$2:A10,A10)=1,1,0) | M10: =_xlfn.XLOOKUP(C10,Customers!$A$2:$A$25,Customers!$B$2:$B$25,"not found") | N10: =_xlfn.XLOOKUP(C10,Customers!$A$2:$A$25,Customers!$D$2:$D$25,"not found")
A11: 10007 | B11: 45681 | C11: 0001 | D11: 101 | E11: 45 | F11: 430 | G11: 0 | H11: Delivered | I11: Neha Kulkarni | J11: =E11*F11*(1-G11/100) | K11: =DATE(YEAR(B11),MONTH(B11),1) | L11: =IF(COUNTIF($A$2:A11,A11)=1,1,0) | M11: =_xlfn.XLOOKUP(C11,Customers!$A$2:$A$25,Customers!$B$2:$B$25,"not found") | N11: =_xlfn.XLOOKUP(C11,Customers!$A$2:$A$25,Customers!$D$2:$D$25,"not found")
A12: 10007 | B12: 45681 | C12: 0001 | D12: 102 | E12: 20 | F12: 750 | G12: 0 | H12: Delivered | I12: Neha Kulkarni | J12: =E12*F12*(1-G12/100) | K12: =DATE(YEAR(B12),MONTH(B12),1) | L12: =IF(COUNTIF($A$2:A12,A12)=1,1,0) | M12: =_xlfn.XLOOKUP(C12,Customers!$A$2:$A$25,Customers!$B$2:$B$25,"not found") | N12: =_xlfn.XLOOKUP(C12,Customers!$A$2:$A$25,Customers!$D$2:$D$25,"not found")
A13: 10007 | B13: 45681 | C13: 0001 | D13: 108 | E13: 20 | F13: 290 | G13: 0 | H13: Delivered | I13: Neha Kulkarni | J13: =E13*F13*(1-G13/100) | K13: =DATE(YEAR(B13),MONTH(B13),1) | L13: =IF(COUNTIF($A$2:A13,A13)=1,1,0) | M13: =_xlfn.XLOOKUP(C13,Customers!$A$2:$A$25,Customers!$B$2:$B$25,"not found") | N13: =_xlfn.XLOOKUP(C13,Customers!$A$2:$A$25,Customers!$D$2:$D$25,"not found")
... A29: 10014 | B29: 45705 | C29: 0007 | D29: 102 | E29: 25 | F29: 750 | G29: 8 | H29: Delivered | I29: Farah Khan | J29: =E29*F29*(1-G29/100) | K29: =DATE(YEAR(B29),MONTH(B29),1) | L29: =IF(COUNTIF($A$2:A29,A29)=1,1,0) | M29: =_xlfn.XLOOKUP(C29,Customers!$A$2:$A$25,Customers!$B$2:$B$25,"not found") | N29: =_xlfn.XLOOKUP(C29,Customers!$A$2:$A$25,Customers!$D$2:$D$25,"not found")
A30: 10015 | B30: 45708 | C30: 0006 | D30: 108 | E30: 20 | F30: 290 | G30: 0 | H30: Delivered | J30: =E30*F30*(1-G30/100) | K30: =DATE(YEAR(B30),MONTH(B30),1) | L30: =IF(COUNTIF($A$2:A30,A30)=1,1,0) | M30: =_xlfn.XLOOKUP(C30,Customers!$A$2:$A$25,Customers!$B$2:$B$25,"not found") | N30: =_xlfn.XLOOKUP(C30,Customers!$A$2:$A$25,Customers!$D$2:$D$25,"not found")
A31: 10016 | B31: 45708 | C31: 0012 | D31: 101 | E31: 25 | F31: 430 | G31: 0 | H31: Delivered | I31: Neha Kulkarni | J31: =E31*F31*(1-G31/100) | K31: =DATE(YEAR(B31),MONTH(B31),1) | L31: =IF(COUNTIF($A$2:A31,A31)=1,1,0) | M31: =_xlfn.XLOOKUP(C31,Customers!$A$2:$A$25,Customers!$B$2:$B$25,"not found") | N31: =_xlfn.XLOOKUP(C31,Customers!$A$2:$A$25,Customers!$D$2:$D$25,"not found")
A32: 10016 | B32: 45708 | C32: 0012 | D32: 103 | E32: 50 | F32: 115 | G32: 5 | H32: Delivered | I32: Neha Kulkarni | J32: =E32*F32*(1-G32/100) | K32: =DATE(YEAR(B32),MONTH(B32),1) | L32: =IF(COUNTIF($A$2:A32,A32)=1,1,0) | M32: =_xlfn.XLOOKUP(C32,Customers!$A$2:$A$25,Customers!$B$2:$B$25,"not found") | N32: =_xlfn.XLOOKUP(C32,Customers!$A$2:$A$25,Customers!$D$2:$D$25,"not found")
A33: 10016 | B33: 45708 | C33: 0012 | D33: 108 | E33: 30 | F33: 290 | G33: 0 | H33: Delivered | I33: Neha Kulkarni | J33: =E33*F33*(1-G33/100) | K33: =DATE(YEAR(B33),MONTH(B33),1) | L33: =IF(COUNTIF($A$2:A33,A33)=1,1,0) | M33: =_xlfn.XLOOKUP(C33,Customers!$A$2:$A$25,Customers!$B$2:$B$25,"not found") | N33: =_xlfn.XLOOKUP(C33,Customers!$A$2:$A$25,Customers!$D$2:$D$25,"not found")
A34: 10017 | B34: 45713 | C34: 0005 | D34: 107 | E34: 40 | F34: 380 | G34: 5 | H34: Delivered | I34: Rahul Mehta | J34: =E34*F34*(1-G34/100) | K34: =DATE(YEAR(B34),MONTH(B34),1) | L34: =IF(COUNTIF($A$2:A34,A34)=1,1,0) | M34: =_xlfn.XLOOKUP(C34,Customers!$A$2:$A$25,Customers!$B$2:$B$25,"not found") | N34: =_xlfn.XLOOKUP(C34,Customers!$A$2:$A$25,Customers!$D$2:$D$25,"not found")
A35: 10018 | B35: 45716 | C35: 0001 | D35: 101 | E35: 25 | F35: 430 | G35: 5 | H35: Delivered | I35: Neha Kulkarni | J35: =E35*F35*(1-G35/100) | K35: =DATE(YEAR(B35),MONTH(B35),1) | L35: =IF(COUNTIF($A$2:A35,A35)=1,1,0) | M35: =_xlfn.XLOOKUP(C35,Customers!$A$2:$A$25,Customers!$B$2:$B$25,"not found") | N35: =_xlfn.XLOOKUP(C35,Customers!$A$2:$A$25,Customers!$D$2:$D$25,"not found")
A36: 10018 | B36: 45716 | C36: 0001 | D36: 108 | E36: 15 | F36: 290 | G36: 0 | H36: Delivered | I36: Neha Kulkarni | J36: =E36*F36*(1-G36/100) | K36: =DATE(YEAR(B36),MONTH(B36),1) | L36: =IF(COUNTIF($A$2:A36,A36)=1,1,0) | M36: =_xlfn.XLOOKUP(C36,Customers!$A$2:$A$25,Customers!$B$2:$B$25,"not found") | N36: =_xlfn.XLOOKUP(C36,Customers!$A$2:$A$25,Customers!$D$2:$D$25,"not found")
A37: 10019 | B37: 45720 | C37: 0003 | D37: 103 | E37: 40 | F37: 115 | G37: 0 | H37: Delivered | I37: Farah Khan | J37: =E37*F37*(1-G37/100) | K37: =DATE(YEAR(B37),MONTH(B37),1) | L37: =IF(COUNTIF($A$2:A37,A37)=1,1,0) | M37: =_xlfn.XLOOKUP(C37,Customers!$A$2:$A$25,Customers!$B$2:$B$25,"not found") | N37: =_xlfn.XLOOKUP(C37,Customers!$A$2:$A$25,Customers!$D$2:$D$25,"not found")
A38: 10019 | B38: 45720 | C38: 0003 | D38: 107 | E38: 35 | F38: 380 | G38: 5 | H38: Delivered | I38: Farah Khan | J38: =E38*F38*(1-G38/100) | K38: =DATE(YEAR(B38),MONTH(B38),1) | L38: =IF(COUNTIF($A$2:A38,A38)=1,1,0) | M38: =_xlfn.XLOOKUP(C38,Customers!$A$2:$A$25,Customers!$B$2:$B$25,"not found") | N38: =_xlfn.XLOOKUP(C38,Customers!$A$2:$A$25,Customers!$D$2:$D$25,"not found")
A39: 10020 | B39: 45726 | C39: 0004 | D39: 101 | E39: 15 | F39: 430 | G39: 5 | H39: Delivered | I39: Rahul Mehta | J39: =E39*F39*(1-G39/100) | K39: =DATE(YEAR(B39),MONTH(B39),1) | L39: =IF(COUNTIF($A$2:A39,A39)=1,1,0) | M39: =_xlfn.XLOOKUP(C39,Customers!$A$2:$A$25,Customers!$B$2:$B$25,"not found") | N39: =_xlfn.XLOOKUP(C39,Customers!$A$2:$A$25,Customers!$D$2:$D$25,"not found")
A40: 10020 | B40: 45726 | C40: 0004 | D40: 102 | E40: 15 | F40: 750 | G40: 12 | H40: Delivered | I40: Rahul Mehta | J40: =E40*F40*(1-G40/100) | K40: =DATE(YEAR(B40),MONTH(B40),1) | L40: =IF(COUNTIF($A$2:A40,A40)=1,1,0) | M40: =_xlfn.XLOOKUP(C40,Customers!$A$2:$A$25,Customers!$B$2:$B$25,"not found") | N40: =_xlfn.XLOOKUP(C40,Customers!$A$2:$A$25,Customers!$D$2:$D$25,"not found")
A41: 10020 | B41: 45726 | C41: 0004 | D41: 105 | E41: 25 | F41: 1400 | G41: 10 | H41: Delivered | I41: Rahul Mehta | J41: =E41*F41*(1-G41/100) | K41: =DATE(YEAR(B41),MONTH(B41),1) | L41: =IF(COUNTIF($A$2:A41,A41)=1,1,0) | M41: =_xlfn.XLOOKUP(C41,Customers!$A$2:$A$25,Customers!$B$2:$B$25,"not found") | N41: =_xlfn.XLOOKUP(C41,Customers!$A$2:$A$25,Customers!$D$2:$D$25,"not found")
A42: 10021 | B42: 45734 | C42: 0005 | D42: 104 | E42: 15 | F42: 620 | G42: 0 | H42: Delivered | I42: Rahul Mehta | J42: =E42*F42*(1-G42/100) | K42: =DATE(YEAR(B42),MONTH(B42),1) | L42: =IF(COUNTIF($A$2:A42,A42)=1,1,0) | M42: =_xlfn.XLOOKUP(C42,Customers!$A$2:$A$25,Customers!$B$2:$B$25,"not found") | N42: =_xlfn.XLOOKUP(C42,Customers!$A$2:$A$25,Customers!$D$2:$D$25,"not found")
... A63: 10035 | B63: 45761 | C63: 0003 | D63: 101 | E63: 25 | F63: 430 | G63: 5 | H63: Delivered | I63: Farah Khan | J63: =E63*F63*(1-G63/100) | K63: =DATE(YEAR(B63),MONTH(B63),1) | L63: =IF(COUNTIF($A$2:A63,A63)=1,1,0) | M63: =_xlfn.XLOOKUP(C63,Customers!$A$2:$A$25,Customers!$B$2:$B$25,"not found") | N63: =_xlfn.XLOOKUP(C63,Customers!$A$2:$A$25,Customers!$D$2:$D$25,"not found")
A64: 10036 | B64: 45762 | C64: 0012 | D64: 103 | E64: 35 | F64: 115 | G64: 0 | H64: Delivered | J64: =E64*F64*(1-G64/100) | K64: =DATE(YEAR(B64),MONTH(B64),1) | L64: =IF(COUNTIF($A$2:A64,A64)=1,1,0) | M64: =_xlfn.XLOOKUP(C64,Customers!$A$2:$A$25,Customers!$B$2:$B$25,"not found") | N64: =_xlfn.XLOOKUP(C64,Customers!$A$2:$A$25,Customers!$D$2:$D$25,"not found")
A65: 10036 | B65: 45762 | C65: 0012 | D65: 104 | E65: 30 | F65: 620 | G65: 5 | H65: Delivered | J65: =E65*F65*(1-G65/100) | K65: =DATE(YEAR(B65),MONTH(B65),1) | L65: =IF(COUNTIF($A$2:A65,A65)=1,1,0) | M65: =_xlfn.XLOOKUP(C65,Customers!$A$2:$A$25,Customers!$B$2:$B$25,"not found") | N65: =_xlfn.XLOOKUP(C65,Customers!$A$2:$A$25,Customers!$D$2:$D$25,"not found")
A66: 10036 | B66: 45762 | C66: 0012 | D66: 107 | E66: 35 | F66: 380 | G66: 0 | H66: Delivered | J66: =E66*F66*(1-G66/100) | K66: =DATE(YEAR(B66),MONTH(B66),1) | L66: =IF(COUNTIF($A$2:A66,A66)=1,1,0) | M66: =_xlfn.XLOOKUP(C66,Customers!$A$2:$A$25,Customers!$B$2:$B$25,"not found") | N66: =_xlfn.XLOOKUP(C66,Customers!$A$2:$A$25,Customers!$D$2:$D$25,"not found")
A67: 10037 | B67: 45767 | C67: 0005 | D67: 101 | E67: 45 | F67: 430 | G67: 0 | H67: Delivered | I67: Rahul Mehta | J67: =E67*F67*(1-G67/100) | K67: =DATE(YEAR(B67),MONTH(B67),1) | L67: =IF(COUNTIF($A$2:A67,A67)=1,1,0) | M67: =_xlfn.XLOOKUP(C67,Customers!$A$2:$A$25,Customers!$B$2:$B$25,"not found") | N67: =_xlfn.XLOOKUP(C67,Customers!$A$2:$A$25,Customers!$D$2:$D$25,"not found")
A68: 10037 | B68: 45767 | C68: 0005 | D68: 108 | E68: 30 | F68: 290 | G68: 5 | H68: Delivered | I68: Rahul Mehta | J68: =E68*F68*(1-G68/100) | K68: =DATE(YEAR(B68),MONTH(B68),1) | L68: =IF(COUNTIF($A$2:A68,A68)=1,1,0) | M68: =_xlfn.XLOOKUP(C68,Customers!$A$2:$A$25,Customers!$B$2:$B$25,"not found") | N68: =_xlfn.XLOOKUP(C68,Customers!$A$2:$A$25,Customers!$D$2:$D$25,"not found")
A69: 10038 | B69: 45768 | C69: 0006 | D69: 107 | E69: 50 | F69: 380 | G69: 0 | H69: Delivered | J69: =E69*F69*(1-G69/100) | K69: =DATE(YEAR(B69),MONTH(B69),1) | L69: =IF(COUNTIF($A$2:A69,A69)=1,1,0) | M69: =_xlfn.XLOOKUP(C69,Customers!$A$2:$A$25,Customers!$B$2:$B$25,"not found") | N69: =_xlfn.XLOOKUP(C69,Customers!$A$2:$A$25,Customers!$D$2:$D$25,"not found")
A70: 10039 | B70: 45769 | C70: 0001 | D70: 102 | E70: 15 | F70: 750 | G70: 5 | H70: Delivered | I70: Neha Kulkarni | J70: =E70*F70*(1-G70/100) | K70: =DATE(YEAR(B70),MONTH(B70),1) | L70: =IF(COUNTIF($A$2:A70,A70)=1,1,0) | M70: =_xlfn.XLOOKUP(C70,Customers!$A$2:$A$25,Customers!$B$2:$B$25,"not found") | N70: =_xlfn.XLOOKUP(C70,Customers!$A$2:$A$25,Customers!$D$2:$D$25,"not found")
A71: 10039 | B71: 45769 | C71: 0001 | D71: 104 | E71: 35 | F71: 620 | G71: 0 | H71: Delivered | I71: Neha Kulkarni | J71: =E71*F71*(1-G71/100) | K71: =DATE(YEAR(B71),MONTH(B71),1) | L71: =IF(COUNTIF($A$2:A71,A71)=1,1,0) | M71: =_xlfn.XLOOKUP(C71,Customers!$A$2:$A$25,Customers!$B$2:$B$25,"not found") | N71: =_xlfn.XLOOKUP(C71,Customers!$A$2:$A$25,Customers!$D$2:$D$25,"not found")
A72: 10040 | B72: 45770 | C72: 0004 | D72: 108 | E72: 25 | F72: 290 | G72: 5 | H72: Delivered | I72: Rahul Mehta | J72: =E72*F72*(1-G72/100) | K72: =DATE(YEAR(B72),MONTH(B72),1) | L72: =IF(COUNTIF($A$2:A72,A72)=1,1,0) | M72: =_xlfn.XLOOKUP(C72,Customers!$A$2:$A$25,Customers!$B$2:$B$25,"not found") | N72: =_xlfn.XLOOKUP(C72,Customers!$A$2:$A$25,Customers!$D$2:$D$25,"not found")
A73: 10041 | B73: 45770 | C73: 0012 | D73: 103 | E73: 35 | F73: 115 | G73: 0 | H73: Delivered | I73: Neha Kulkarni | J73: =E73*F73*(1-G73/100) | K73: =DATE(YEAR(B73),MONTH(B73),1) | L73: =IF(COUNTIF($A$2:A73,A73)=1,1,0) | M73: =_xlfn.XLOOKUP(C73,Customers!$A$2:$A$25,Customers!$B$2:$B$25,"not found") | N73: =_xlfn.XLOOKUP(C73,Customers!$A$2:$A$25,Customers!$D$2:$D$25,"not found")
A74: 10041 | B74: 45770 | C74: 0012 | D74: 108 | E74: 60 | F74: 290 | G74: 5 | H74: Delivered | I74: Neha Kulkarni | J74: =E74*F74*(1-G74/100) | K74: =DATE(YEAR(B74),MONTH(B74),1) | L74: =IF(COUNTIF($A$2:A74,A74)=1,1,0) | M74: =_xlfn.XLOOKUP(C74,Customers!$A$2:$A$25,Customers!$B$2:$B$25,"not found") | N74: =_xlfn.XLOOKUP(C74,Customers!$A$2:$A$25,Customers!$D$2:$D$25,"not found")
A75: 10042 | B75: 45772 | C75: 0007 | D75: 102 | E75: 10 | F75: 750 | G75: 5 | H75: Delivered | I75: Farah Khan | J75: =E75*F75*(1-G75/100) | K75: =DATE(YEAR(B75),MONTH(B75),1) | L75: =IF(COUNTIF($A$2:A75,A75)=1,1,0) | M75: =_xlfn.XLOOKUP(C75,Customers!$A$2:$A$25,Customers!$B$2:$B$25,"not found") | N75: =_xlfn.XLOOKUP(C75,Customers!$A$2:$A$25,Customers!$D$2:$D$25,"not found")
A76: 10043 | B76: 45781 | C76: 0002 | D76: 102 | E76: 15 | F76: 750 | G76: 0 | H76: Delivered | I76: Neha Kulkarni | J76: =E76*F76*(1-G76/100) | K76: =DATE(YEAR(B76),MONTH(B76),1) | L76: =IF(COUNTIF($A$2:A76,A76)=1,1,0) | M76: =_xlfn.XLOOKUP(C76,Customers!$A$2:$A$25,Customers!$B$2:$B$25,"not found") | N76: =_xlfn.XLOOKUP(C76,Customers!$A$2:$A$25,Customers!$D$2:$D$25,"not found")
A77: 10043 | B77: 45781 | C77: 0002 | D77: 104 | E77: 20 | F77: 620 | G77: 0 | H77: Delivered | I77: Neha Kulkarni | J77: =E77*F77*(1-G77/100) | K77: =DATE(YEAR(B77),MONTH(B77),1) | L77: =IF(COUNTIF($A$2:A77,A77)=1,1,0) | M77: =_xlfn.XLOOKUP(C77,Customers!$A$2:$A$25,Customers!$B$2:$B$25,"not found") | N77: =_xlfn.XLOOKUP(C77,Customers!$A$2:$A$25,Customers!$D$2:$D$25,"not found")
A78: 10044 | B78: 45781 | C78: 0004 | D78: 101 | E78: 15 | F78: 430 | G78: 8 | H78: Delivered | I78: Rahul Mehta | J78: =E78*F78*(1-G78/100) | K78: =DATE(YEAR(B78),MONTH(B78),1) | L78: =IF(COUNTIF($A$2:A78,A78)=1,1,0) | M78: =_xlfn.XLOOKUP(C78,Customers!$A$2:$A$25,Customers!$B$2:$B$25,"not found") | N78: =_xlfn.XLOOKUP(C78,Customers!$A$2:$A$25,Customers!$D$2:$D$25,"not found")
A79: 10044 | B79: 45781 | C79: 0004 | D79: 105 | E79: 35 | F79: 1400 | G79: 10 | H79: Delivered | I79: Rahul Mehta | J79: =E79*F79*(1-G79/100) | K79: =DATE(YEAR(B79),MONTH(B79),1) | L79: =IF(COUNTIF($A$2:A79,A79)=1,1,0) | M79: =_xlfn.XLOOKUP(C79,Customers!$A$2:$A$25,Customers!$B$2:$B$25,"not found") | N79: =_xlfn.XLOOKUP(C79,Customers!$A$2:$A$25,Customers!$D$2:$D$25,"not found")
A80: 10044 | B80: 45781 | C80: 0004 | D80: 108 | E80: 5 | F80: 290 | G80: 12 | H80: Delivered | I80: Rahul Mehta | J80: =E80*F80*(1-G80/100) | K80: =DATE(YEAR(B80),MONTH(B80),1) | L80: =IF(COUNTIF($A$2:A80,A80)=1,1,0) | M80: =_xlfn.XLOOKUP(C80,Customers!$A$2:$A$25,Customers!$B$2:$B$25,"not found") | N80: =_xlfn.XLOOKUP(C80,Customers!$A$2:$A$25,Customers!$D$2:$D$25,"not found")
A81: 10045 | B81: 45781 | C81: 0013 | D81: 102 | E81: 25 | F81: 750 | G81: 0 | H81: Delivered | I81: Neha Kulkarni | J81: =E81*F81*(1-G81/100) | K81: =DATE(YEAR(B81),MONTH(B81),1) | L81: =IF(COUNTIF($A$2:A81,A81)=1,1,0) | M81: =_xlfn.XLOOKUP(C81,Customers!$A$2:$A$25,Customers!$B$2:$B$25,"not found") | N81: =_xlfn.XLOOKUP(C81,Customers!$A$2:$A$25,Customers!$D$2:$D$25,"not found")
... A99: 10053 | B99: 45797 | C99: 0003 | D99: 108 | E99: 50 | F99: 290 | G99: 5 | H99: Delivered | I99: Farah Khan | J99: =E99*F99*(1-G99/100) | K99: =DATE(YEAR(B99),MONTH(B99),1) | L99: =IF(COUNTIF($A$2:A99,A99)=1,1,0) | M99: =_xlfn.XLOOKUP(C99,Customers!$A$2:$A$25,Customers!$B$2:$B$25,"not found") | N99: =_xlfn.XLOOKUP(C99,Customers!$A$2:$A$25,Customers!$D$2:$D$25,"not found")
A100: 10054 | B100: 45798 | C100: 0006 | D100: 107 | E100: 35 | F100: 380 | G100: 5 | H100: Delivered | J100: =E100*F100*(1-G100/100) | K100: =DATE(YEAR(B100),MONTH(B100),1) | L100: =IF(COUNTIF($A$2:A100,A100)=1,1,0) | M100: =_xlfn.XLOOKUP(C100,Customers!$A$2:$A$25,Customers!$B$2:$B$25,"not found") | N100: =_xlfn.XLOOKUP(C100,Customers!$A$2:$A$25,Customers!$D$2:$D$25,"not found")
A101: 10055 | B101: 45798 | C101: 0008 | D101: 103 | E101: 20 | F101: 115 | G101: 0 | H101: Delivered | I101: Neha Kulkarni | J101: =E101*F101*(1-G101/100) | K101: =DATE(YEAR(B101),MONTH(B101),1) | L101: =IF(COUNTIF($A$2:A101,A101)=1,1,0) | M101: =_xlfn.XLOOKUP(C101,Customers!$A$2:$A$25,Customers!$B$2:$B$25,"not found") | N101: =_xlfn.XLOOKUP(C101,Customers!$A$2:$A$25,Customers!$D$2:$D$25,"not found")
A102: 10056 | B102: 45799 | C102: 0009 | D102: 103 | E102: 25 | F102: 115 | G102: 5 | H102: Delivered | I102: Farah Khan | J102: =E102*F102*(1-G102/100) | K102: =DATE(YEAR(B102),MONTH(B102),1) | L102: =IF(COUNTIF($A$2:A102,A102)=1,1,0) | M102: =_xlfn.XLOOKUP(C102,Customers!$A$2:$A$25,Customers!$B$2:$B$25,"not found") | N102: =_xlfn.XLOOKUP(C102,Customers!$A$2:$A$25,Customers!$D$2:$D$25,"not found")
A103: 10056 | B103: 45799 | C103: 0009 | D103: 108 | E103: 30 | F103: 290 | G103: 5 | H103: Delivered | I103: Farah Khan | J103: =E103*F103*(1-G103/100) | K103: =DATE(YEAR(B103),MONTH(B103),1) | L103: =IF(COUNTIF($A$2:A103,A103)=1,1,0) | M103: =_xlfn.XLOOKUP(C103,Customers!$A$2:$A$25,Customers!$B$2:$B$25,"not found") | N103: =_xlfn.XLOOKUP(C103,Customers!$A$2:$A$25,Customers!$D$2:$D$25,"not found")
A104: 10057 | B104: 45804 | C104: 0011 | D104: 105 | E104: 35 | F104: 1400 | G104: 10 | H104: Delivered | I104: Rahul Mehta | J104: =E104*F104*(1-G104/100) | K104: =DATE(YEAR(B104),MONTH(B104),1) | L104: =IF(COUNTIF($A$2:A104,A104)=1,1,0) | M104: =_xlfn.XLOOKUP(C104,Customers!$A$2:$A$25,Customers!$B$2:$B$25,"not found") | N104: =_xlfn.XLOOKUP(C104,Customers!$A$2:$A$25,Customers!$D$2:$D$25,"not found")
A105: 10058 | B105: 45809 | C105: 0012 | D105: 101 | E105: 30 | F105: 430 | G105: 0 | H105: Delivered | I105: Neha Kulkarni | J105: =E105*F105*(1-G105/100) | K105: =DATE(YEAR(B105),MONTH(B105),1) | L105: =IF(COUNTIF($A$2:A105,A105)=1,1,0) | M105: =_xlfn.XLOOKUP(C105,Customers!$A$2:$A$25,Customers!$B$2:$B$25,"not found") | N105: =_xlfn.XLOOKUP(C105,Customers!$A$2:$A$25,Customers!$D$2:$D$25,"not found")
A106: 10058 | B106: 45809 | C106: 0012 | D106: 108 | E106: 25 | F106: 290 | G106: 5 | H106: Delivered | I106: Neha Kulkarni | J106: =E106*F106*(1-G106/100) | K106: =DATE(YEAR(B106),MONTH(B106),1) | L106: =IF(COUNTIF($A$2:A106,A106)=1,1,0) | M106: =_xlfn.XLOOKUP(C106,Customers!$A$2:$A$25,Customers!$B$2:$B$25,"not found") | N106: =_xlfn.XLOOKUP(C106,Customers!$A$2:$A$25,Customers!$D$2:$D$25,"not found")
A107: 10059 | B107: 45812 | C107: 0001 | D107: 102 | E107: 5 | F107: 750 | G107: 0 | H107: Delivered | I107: Neha Kulkarni | J107: =E107*F107*(1-G107/100) | K107: =DATE(YEAR(B107),MONTH(B107),1) | L107: =IF(COUNTIF($A$2:A107,A107)=1,1,0) | M107: =_xlfn.XLOOKUP(C107,Customers!$A$2:$A$25,Customers!$B$2:$B$25,"not found") | N107: =_xlfn.XLOOKUP(C107,Customers!$A$2:$A$25,Customers!$D$2:$D$25,"not found")
A108: 10060 | B108: 45814 | C108: 0004 | D108: 108 | E108: 30 | F108: 290 | G108: 5 | H108: Delivered | I108: Rahul Mehta | J108: =E108*F108*(1-G108/100) | K108: =DATE(YEAR(B108),MONTH(B108),1) | L108: =IF(COUNTIF($A$2:A108,A108)=1,1,0) | M108: =_xlfn.XLOOKUP(C108,Customers!$A$2:$A$25,Customers!$B$2:$B$25,"not found") | N108: =_xlfn.XLOOKUP(C108,Customers!$A$2:$A$25,Customers!$D$2:$D$25,"not found")
A109: 10061 | B109: 45817 | C109: 0015 | D109: 108 | E109: 5 | F109: 290 | G109: 5 | H109: Delivered | I109: Farah Khan | J109: =E109*F109*(1-G109/100) | K109: =DATE(YEAR(B109),MONTH(B109),1) | L109: =IF(COUNTIF($A$2:A109,A109)=1,1,0) | M109: =_xlfn.XLOOKUP(C109,Customers!$A$2:$A$25,Customers!$B$2:$B$25,"not found") | N109: =_xlfn.XLOOKUP(C109,Customers!$A$2:$A$25,Customers!$D$2:$D$25,"not found")
A110: 10062 | B110: 45818 | C110: 0002 | D110: 104 | E110: 10 | F110: 620 | G110: 5 | H110: Delivered | I110: Neha Kulkarni | J110: =E110*F110*(1-G110/100) | K110: =DATE(YEAR(B110),MONTH(B110),1) | L110: =IF(COUNTIF($A$2:A110,A110)=1,1,0) | M110: =_xlfn.XLOOKUP(C110,Customers!$A$2:$A$25,Customers!$B$2:$B$25,"not found") | N110: =_xlfn.XLOOKUP(C110,Customers!$A$2:$A$25,Customers!$D$2:$D$25,"not found")
A111: 10062 | B111: 45818 | C111: 0002 | D111: 108 | E111: 30 | F111: 290 | G111: 5 | H111: Delivered | I111: Neha Kulkarni | J111: =E111*F111*(1-G111/100) | K111: =DATE(YEAR(B111),MONTH(B111),1) | L111: =IF(COUNTIF($A$2:A111,A111)=1,1,0) | M111: =_xlfn.XLOOKUP(C111,Customers!$A$2:$A$25,Customers!$B$2:$B$25,"not found") | N111: =_xlfn.XLOOKUP(C111,Customers!$A$2:$A$25,Customers!$D$2:$D$25,"not found")
A112: 10063 | B112: 45818 | C112: 0006 | D112: 101 | E112: 20 | F112: 430 | G112: 0 | H112: Delivered | J112: =E112*F112*(1-G112/100) | K112: =DATE(YEAR(B112),MONTH(B112),1) | L112: =IF(COUNTIF($A$2:A112,A112)=1,1,0) | M112: =_xlfn.XLOOKUP(C112,Customers!$A$2:$A$25,Customers!$B$2:$B$25,"not found") | N112: =_xlfn.XLOOKUP(C112,Customers!$A$2:$A$25,Customers!$D$2:$D$25,"not found")
A113: 10063 | B113: 45818 | C113: 0006 | D113: 103 | E113: 15 | F113: 115 | G113: 5 | H113: Delivered | J113: =E113*F113*(1-G113/100) | K113: =DATE(YEAR(B113),MONTH(B113),1) | L113: =IF(COUNTIF($A$2:A113,A113)=1,1,0) | M113: =_xlfn.XLOOKUP(C113,Customers!$A$2:$A$25,Customers!$B$2:$B$25,"not found") | N113: =_xlfn.XLOOKUP(C113,Customers!$A$2:$A$25,Customers!$D$2:$D$25,"not found")
A114: 10064 | B114: 45818 | C114: 0011 | D114: 101 | E114: 15 | F114: 430 | G114: 12 | H114: Delivered | I114: Rahul Mehta | J114: =E114*F114*(1-G114/100) | K114: =DATE(YEAR(B114),MONTH(B114),1) | L114: =IF(COUNTIF($A$2:A114,A114)=1,1,0) | M114: =_xlfn.XLOOKUP(C114,Customers!$A$2:$A$25,Customers!$B$2:$B$25,"not found") | N114: =_xlfn.XLOOKUP(C114,Customers!$A$2:$A$25,Customers!$D$2:$D$25,"not found")
A115: 10064 | B115: 45818 | C115: 0011 | D115: 102 | E115: 15 | F115: 750 | G115: 5 | H115: Delivered | I115: Rahul Mehta | J115: =E115*F115*(1-G115/100) | K115: =DATE(YEAR(B115),MONTH(B115),1) | L115: =IF(COUNTIF($A$2:A115,A115)=1,1,0) | M115: =_xlfn.XLOOKUP(C115,Customers!$A$2:$A$25,Customers!$B$2:$B$25,"not found") | N115: =_xlfn.XLOOKUP(C115,Customers!$A$2:$A$25,Customers!$D$2:$D$25,"not found")
A116: 10064 | B116: 45818 | C116: 0011 | D116: 105 | E116: 5 | F116: 1400 | G116: 12 | H116: Delivered | I116: Rahul Mehta | J116: =E116*F116*(1-G116/100) | K116: =DATE(YEAR(B116),MONTH(B116),1) | L116: =IF(COUNTIF($A$2:A116,A116)=1,1,0) | M116: =_xlfn.XLOOKUP(C116,Customers!$A$2:$A$25,Customers!$B$2:$B$25,"not found") | N116: =_xlfn.XLOOKUP(C116,Customers!$A$2:$A$25,Customers!$D$2:$D$25,"not found")
A117: 10065 | B117: 45818 | C117: 0015 | D117: 101 | E117: 5 | F117: 430 | G117: 5 | H117: Delivered | I117: Farah Khan | J117: =E117*F117*(1-G117/100) | K117: =DATE(YEAR(B117),MONTH(B117),1) | L117: =IF(COUNTIF($A$2:A117,A117)=1,1,0) | M117: =_xlfn.XLOOKUP(C117,Customers!$A$2:$A$25,Customers!$B$2:$B$25,"not found") | N117: =_xlfn.XLOOKUP(C117,Customers!$A$2:$A$25,Customers!$D$2:$D$25,"not found")
A118: 10066 | B118: 45821 | C118: 0007 | D118: 105 | E118: 20 | F118: 1400 | G118: 5 | H118: Delivered | I118: Farah Khan | J118: =E118*F118*(1-G118/100) | K118: =DATE(YEAR(B118),MONTH(B118),1) | L118: =IF(COUNTIF($A$2:A118,A118)=1,1,0) | M118: =_xlfn.XLOOKUP(C118,Customers!$A$2:$A$25,Customers!$B$2:$B$25,"not found") | N118: =_xlfn.XLOOKUP(C118,Customers!$A$2:$A$25,Customers!$D$2:$D$25,"not found")
A119: 10066 | B119: 45821 | C119: 0007 | D119: 108 | E119: 15 | F119: 290 | G119: 8 | H119: Delivered | I119: Farah Khan | J119: =E119*F119*(1-G119/100) | K119: =DATE(YEAR(B119),MONTH(B119),1) | L119: =IF(COUNTIF($A$2:A119,A119)=1,1,0) | M119: =_xlfn.XLOOKUP(C119,Customers!$A$2:$A$25,Customers!$B$2:$B$25,"not found") | N119: =_xlfn.XLOOKUP(C119,Customers!$A$2:$A$25,Customers!$D$2:$D$25,"not found")
A120: 10067 | B120: 45822 | C120: 0013 | D120: 103 | E120: 25 | F120: 115 | G120: 5 | H120: Delivered | I120: Neha Kulkarni | J120: =E120*F120*(1-G120/100) | K120: =DATE(YEAR(B120),MONTH(B120),1) | L120: =IF(COUNTIF($A$2:A120,A120)=1,1,0) | M120: =_xlfn.XLOOKUP(C120,Customers!$A$2:$A$25,Customers!$B$2:$B$25,"not found") | N120: =_xlfn.XLOOKUP(C120,Customers!$A$2:$A$25,Customers!$D$2:$D$25,"not found")
A121: 10067 | B121: 45822 | C121: 0013 | D121: 108 | E121: 25 | F121: 290 | G121: 0 | H121: Delivered | I121: Neha Kulkarni | J121: =E121*F121*(1-G121/100) | K121: =DATE(YEAR(B121),MONTH(B121),1) | L121: =IF(COUNTIF($A$2:A121,A121)=1,1,0) | M121: =_xlfn.XLOOKUP(C121,Customers!$A$2:$A$25,Customers!$B$2:$B$25,"not found") | N121: =_xlfn.XLOOKUP(C121,Customers!$A$2:$A$25,Customers!$D$2:$D$25,"not found")
A122: 10068 | B122: 45826 | C122: 0005 | D122: 101 | E122: 15 | F122: 430 | G122: 0 | H122: Delivered | I122: Rahul Mehta | J122: =E122*F122*(1-G122/100) | K122: =DATE(YEAR(B122),MONTH(B122),1) | L122: =IF(COUNTIF($A$2:A122,A122)=1,1,0) | M122: =_xlfn.XLOOKUP(C122,Customers!$A$2:$A$25,Customers!$B$2:$B$25,"not found") | N122: =_xlfn.XLOOKUP(C122,Customers!$A$2:$A$25,Customers!$D$2:$D$25,"not found")
A123: 10069 | B123: 45832 | C123: 0003 | D123: 101 | E123: 20 | F123: 430 | G123: 0 | H123: Delivered | I123: Farah Khan | J123: =E123*F123*(1-G123/100) | K123: =DATE(YEAR(B123),MONTH(B123),1) | L123: =IF(COUNTIF($A$2:A123,A123)=1,1,0) | M123: =_xlfn.XLOOKUP(C123,Customers!$A$2:$A$25,Customers!$B$2:$B$25,"not found") | N123: =_xlfn.XLOOKUP(C123,Customers!$A$2:$A$25,Customers!$D$2:$D$25,"not found")
A124: 10069 | B124: 45832 | C124: 0003 | D124: 104 | E124: 25 | F124: 620 | G124: 5 | H124: Delivered | I124: Farah Khan | J124: =E124*F124*(1-G124/100) | K124: =DATE(YEAR(B124),MONTH(B124),1) | L124: =IF(COUNTIF($A$2:A124,A124)=1,1,0) | M124: =_xlfn.XLOOKUP(C124,Customers!$A$2:$A$25,Customers!$B$2:$B$25,"not found") | N124: =_xlfn.XLOOKUP(C124,Customers!$A$2:$A$25,Customers!$D$2:$D$25,"not found")
A125: 10070 | B125: 45836 | C125: 0014 | D125: 105 | E125: 20 | F125: 1400 | G125: 5 | H125: Delivered | I125: Farah Khan | J125: =E125*F125*(1-G125/100) | K125: =DATE(YEAR(B125),MONTH(B125),1) | L125: =IF(COUNTIF($A$2:A125,A125)=1,1,0) | M125: =_xlfn.XLOOKUP(C125,Customers!$A$2:$A$25,Customers!$B$2:$B$25,"not found") | N125: =_xlfn.XLOOKUP(C125,Customers!$A$2:$A$25,Customers!$D$2:$D$25,"not found")
... A206: 10107 | B206: 45913 | C206: 0014 | D206: 105 | E206: 45 | F206: 1400 | G206: 10 | H206: Delivered | I206: Farah Khan | J206: =E206*F206*(1-G206/100) | K206: =DATE(YEAR(B206),MONTH(B206),1) | L206: =IF(COUNTIF($A$2:A206,A206)=1,1,0) | M206: =_xlfn.XLOOKUP(C206,Customers!$A$2:$A$25,Customers!$B$2:$B$25,"not found") | N206: =_xlfn.XLOOKUP(C206,Customers!$A$2:$A$25,Customers!$D$2:$D$25,"not found")
A207: 10108 | B207: 45915 | C207: 0022 | D207: 101 | E207: 30 | F207: 430 | G207: 0 | H207: Delivered | J207: =E207*F207*(1-G207/100) | K207: =DATE(YEAR(B207),MONTH(B207),1) | L207: =IF(COUNTIF($A$2:A207,A207)=1,1,0) | M207: =_xlfn.XLOOKUP(C207,Customers!$A$2:$A$25,Customers!$B$2:$B$25,"not found") | N207: =_xlfn.XLOOKUP(C207,Customers!$A$2:$A$25,Customers!$D$2:$D$25,"not found")
A208: 10108 | B208: 45915 | C208: 0022 | D208: 107 | E208: 35 | F208: 380 | G208: 0 | H208: Delivered | J208: =E208*F208*(1-G208/100) | K208: =DATE(YEAR(B208),MONTH(B208),1) | L208: =IF(COUNTIF($A$2:A208,A208)=1,1,0) | M208: =_xlfn.XLOOKUP(C208,Customers!$A$2:$A$25,Customers!$B$2:$B$25,"not found") | N208: =_xlfn.XLOOKUP(C208,Customers!$A$2:$A$25,Customers!$D$2:$D$25,"not found")
A209: 10109 | B209: 45918 | C209: 0009 | D209: 107 | E209: 15 | F209: 380 | G209: 0 | H209: Delivered | I209: Farah Khan | J209: =E209*F209*(1-G209/100) | K209: =DATE(YEAR(B209),MONTH(B209),1) | L209: =IF(COUNTIF($A$2:A209,A209)=1,1,0) | M209: =_xlfn.XLOOKUP(C209,Customers!$A$2:$A$25,Customers!$B$2:$B$25,"not found") | N209: =_xlfn.XLOOKUP(C209,Customers!$A$2:$A$25,Customers!$D$2:$D$25,"not found")
A210: 10109 | B210: 45918 | C210: 0009 | D210: 108 | E210: 35 | F210: 290 | G210: 0 | H210: Delivered | I210: Farah Khan | J210: =E210*F210*(1-G210/100) | K210: =DATE(YEAR(B210),MONTH(B210),1) | L210: =IF(COUNTIF($A$2:A210,A210)=1,1,0) | M210: =_xlfn.XLOOKUP(C210,Customers!$A$2:$A$25,Customers!$B$2:$B$25,"not found") | N210: =_xlfn.XLOOKUP(C210,Customers!$A$2:$A$25,Customers!$D$2:$D$25,"not found")
A211: 10110 | B211: 45921 | C211: 0001 | D211: 104 | E211: 35 | F211: 620 | G211: 0 | H211: Delivered | I211: Neha Kulkarni | J211: =E211*F211*(1-G211/100) | K211: =DATE(YEAR(B211),MONTH(B211),1) | L211: =IF(COUNTIF($A$2:A211,A211)=1,1,0) | M211: =_xlfn.XLOOKUP(C211,Customers!$A$2:$A$25,Customers!$B$2:$B$25,"not found") | N211: =_xlfn.XLOOKUP(C211,Customers!$A$2:$A$25,Customers!$D$2:$D$25,"not found")
A212: 10110 | B212: 45921 | C212: 0001 | D212: 107 | E212: 25 | F212: 380 | G212: 5 | H212: Delivered | I212: Neha Kulkarni | J212: =E212*F212*(1-G212/100) | K212: =DATE(YEAR(B212),MONTH(B212),1) | L212: =IF(COUNTIF($A$2:A212,A212)=1,1,0) | M212: =_xlfn.XLOOKUP(C212,Customers!$A$2:$A$25,Customers!$B$2:$B$25,"not found") | N212: =_xlfn.XLOOKUP(C212,Customers!$A$2:$A$25,Customers!$D$2:$D$25,"not found")
A213: 10111 | B213: 45922 | C213: 0003 | D213: 101 | E213: 30 | F213: 430 | G213: 0 | H213: Delivered | I213: Farah Khan | J213: =E213*F213*(1-G213/100) | K213: =DATE(YEAR(B213),MONTH(B213),1) | L213: =IF(COUNTIF($A$2:A213,A213)=1,1,0) | M213: =_xlfn.XLOOKUP(C213,Customers!$A$2:$A$25,Customers!$B$2:$B$25,"not found") | N213: =_xlfn.XLOOKUP(C213,Customers!$A$2:$A$25,Customers!$D$2:$D$25,"not found")
A214: 10112 | B214: 45922 | C214: 0003 | D214: 101 | E214: 10 | F214: 430 | G214: 5 | H214: Delivered | I214: Farah Khan | J214: =E214*F214*(1-G214/100) | K214: =DATE(YEAR(B214),MONTH(B214),1) | L214: =IF(COUNTIF($A$2:A214,A214)=1,1,0) | M214: =_xlfn.XLOOKUP(C214,Customers!$A$2:$A$25,Customers!$B$2:$B$25,"not found") | N214: =_xlfn.XLOOKUP(C214,Customers!$A$2:$A$25,Customers!$D$2:$D$25,"not found")
A215: 10112 | B215: 45922 | C215: 0003 | D215: 104 | E215: 15 | F215: 620 | G215: 5 | H215: Delivered | I215: Farah Khan | J215: =E215*F215*(1-G215/100) | K215: =DATE(YEAR(B215),MONTH(B215),1) | L215: =IF(COUNTIF($A$2:A215,A215)=1,1,0) | M215: =_xlfn.XLOOKUP(C215,Customers!$A$2:$A$25,Customers!$B$2:$B$25,"not found") | N215: =_xlfn.XLOOKUP(C215,Customers!$A$2:$A$25,Customers!$D$2:$D$25,"not found")
A216: 10112 | B216: 45922 | C216: 0003 | D216: 107 | E216: 60 | F216: 380 | G216: 5 | H216: Delivered | I216: Farah Khan | J216: =E216*F216*(1-G216/100) | K216: =DATE(YEAR(B216),MONTH(B216),1) | L216: =IF(COUNTIF($A$2:A216,A216)=1,1,0) | M216: =_xlfn.XLOOKUP(C216,Customers!$A$2:$A$25,Customers!$B$2:$B$25,"not found") | N216: =_xlfn.XLOOKUP(C216,Customers!$A$2:$A$25,Customers!$D$2:$D$25,"not found")
A217: 10113 | B217: 45923 | C217: 0005 | D217: 101 | E217: 25 | F217: 430 | G217: 5 | H217: Delivered | I217: Rahul Mehta | J217: =E217*F217*(1-G217/100) | K217: =DATE(YEAR(B217),MONTH(B217),1) | L217: =IF(COUNTIF($A$2:A217,A217)=1,1,0) | M217: =_xlfn.XLOOKUP(C217,Customers!$A$2:$A$25,Customers!$B$2:$B$25,"not found") | N217: =_xlfn.XLOOKUP(C217,Customers!$A$2:$A$25,Customers!$D$2:$D$25,"not found")
A218: 10113 | B218: 45923 | C218: 0005 | D218: 102 | E218: 10 | F218: 750 | G218: 0 | H218: Delivered | I218: Rahul Mehta | J218: =E218*F218*(1-G218/100) | K218: =DATE(YEAR(B218),MONTH(B218),1) | L218: =IF(COUNTIF($A$2:A218,A218)=1,1,0) | M218: =_xlfn.XLOOKUP(C218,Customers!$A$2:$A$25,Customers!$B$2:$B$25,"not found") | N218: =_xlfn.XLOOKUP(C218,Customers!$A$2:$A$25,Customers!$D$2:$D$25,"not found")
A219: 10113 | B219: 45923 | C219: 0005 | D219: 107 | E219: 20 | F219: 380 | G219: 5 | H219: Delivered | I219: Rahul Mehta | J219: =E219*F219*(1-G219/100) | K219: =DATE(YEAR(B219),MONTH(B219),1) | L219: =IF(COUNTIF($A$2:A219,A219)=1,1,0) | M219: =_xlfn.XLOOKUP(C219,Customers!$A$2:$A$25,Customers!$B$2:$B$25,"not found") | N219: =_xlfn.XLOOKUP(C219,Customers!$A$2:$A$25,Customers!$D$2:$D$25,"not found")
A220: 10114 | B220: 45924 | C220: 0007 | D220: 101 | E220: 25 | F220: 430 | G220: 12 | H220: Delivered | I220: Farah Khan | J220: =E220*F220*(1-G220/100) | K220: =DATE(YEAR(B220),MONTH(B220),1) | L220: =IF(COUNTIF($A$2:A220,A220)=1,1,0) | M220: =_xlfn.XLOOKUP(C220,Customers!$A$2:$A$25,Customers!$B$2:$B$25,"not found") | N220: =_xlfn.XLOOKUP(C220,Customers!$A$2:$A$25,Customers!$D$2:$D$25,"not found")
... A251: 10130 | B251: 45948 | C251: 0007 | D251: 102 | E251: 20 | F251: 750 | G251: 10 | H251: Delivered | I251: Farah Khan | J251: =E251*F251*(1-G251/100) | K251: =DATE(YEAR(B251),MONTH(B251),1) | L251: =IF(COUNTIF($A$2:A251,A251)=1,1,0) | M251: =_xlfn.XLOOKUP(C251,Customers!$A$2:$A$25,Customers!$B$2:$B$25,"not found") | N251: =_xlfn.XLOOKUP(C251,Customers!$A$2:$A$25,Customers!$D$2:$D$25,"not found")
A252: 10131 | B252: 45948 | C252: 0022 | D252: 103 | E252: 70 | F252: 115 | G252: 0 | H252: Cancelled | J252: =E252*F252*(1-G252/100) | K252: =DATE(YEAR(B252),MONTH(B252),1) | L252: =IF(COUNTIF($A$2:A252,A252)=1,1,0) | M252: =_xlfn.XLOOKUP(C252,Customers!$A$2:$A$25,Customers!$B$2:$B$25,"not found") | N252: =_xlfn.XLOOKUP(C252,Customers!$A$2:$A$25,Customers!$D$2:$D$25,"not found")
A253: 10131 | B253: 45948 | C253: 0022 | D253: 107 | E253: 25 | F253: 380 | G253: 0 | H253: Cancelled | J253: =E253*F253*(1-G253/100) | K253: =DATE(YEAR(B253),MONTH(B253),1) | L253: =IF(COUNTIF($A$2:A253,A253)=1,1,0) | M253: =_xlfn.XLOOKUP(C253,Customers!$A$2:$A$25,Customers!$B$2:$B$25,"not found") | N253: =_xlfn.XLOOKUP(C253,Customers!$A$2:$A$25,Customers!$D$2:$D$25,"not found")
A254: 10131 | B254: 45948 | C254: 0022 | D254: 108 | E254: 70 | F254: 290 | G254: 0 | H254: Cancelled | J254: =E254*F254*(1-G254/100) | K254: =DATE(YEAR(B254),MONTH(B254),1) | L254: =IF(COUNTIF($A$2:A254,A254)=1,1,0) | M254: =_xlfn.XLOOKUP(C254,Customers!$A$2:$A$25,Customers!$B$2:$B$25,"not found") | N254: =_xlfn.XLOOKUP(C254,Customers!$A$2:$A$25,Customers!$D$2:$D$25,"not found")
A255: 10132 | B255: 45950 | C255: 0001 | D255: 101 | E255: 65 | F255: 430 | G255: 0 | H255: Delivered | I255: Neha Kulkarni | J255: =E255*F255*(1-G255/100) | K255: =DATE(YEAR(B255),MONTH(B255),1) | L255: =IF(COUNTIF($A$2:A255,A255)=1,1,0) | M255: =_xlfn.XLOOKUP(C255,Customers!$A$2:$A$25,Customers!$B$2:$B$25,"not found") | N255: =_xlfn.XLOOKUP(C255,Customers!$A$2:$A$25,Customers!$D$2:$D$25,"not found")
A256: 10133 | B256: 45955 | C256: 0001 | D256: 102 | E256: 70 | F256: 750 | G256: 5 | H256: Delivered | I256: Neha Kulkarni | J256: =E256*F256*(1-G256/100) | K256: =DATE(YEAR(B256),MONTH(B256),1) | L256: =IF(COUNTIF($A$2:A256,A256)=1,1,0) | M256: =_xlfn.XLOOKUP(C256,Customers!$A$2:$A$25,Customers!$B$2:$B$25,"not found") | N256: =_xlfn.XLOOKUP(C256,Customers!$A$2:$A$25,Customers!$D$2:$D$25,"not found")
A257: 10133 | B257: 45955 | C257: 0001 | D257: 107 | E257: 50 | F257: 380 | G257: 0 | H257: Delivered | I257: Neha Kulkarni | J257: =E257*F257*(1-G257/100) | K257: =DATE(YEAR(B257),MONTH(B257),1) | L257: =IF(COUNTIF($A$2:A257,A257)=1,1,0) | M257: =_xlfn.XLOOKUP(C257,Customers!$A$2:$A$25,Customers!$B$2:$B$25,"not found") | N257: =_xlfn.XLOOKUP(C257,Customers!$A$2:$A$25,Customers!$D$2:$D$25,"not found")
A258: 10134 | B258: 45956 | C258: 0020 | D258: 103 | E258: 50 | F258: 115 | G258: 0 | H258: Delivered | I258: Neha Kulkarni | J258: =E258*F258*(1-G258/100) | K258: =DATE(YEAR(B258),MONTH(B258),1) | L258: =IF(COUNTIF($A$2:A258,A258)=1,1,0) | M258: =_xlfn.XLOOKUP(C258,Customers!$A$2:$A$25,Customers!$B$2:$B$25,"not found") | N258: =_xlfn.XLOOKUP(C258,Customers!$A$2:$A$25,Customers!$D$2:$D$25,"not found")
A259: 10135 | B259: 45957 | C259: 0004 | D259: 102 | E259: 15 | F259: 750 | G259: 12 | H259: Delivered | I259: Rahul Mehta | J259: =E259*F259*(1-G259/100) | K259: =DATE(YEAR(B259),MONTH(B259),1) | L259: =IF(COUNTIF($A$2:A259,A259)=1,1,0) | M259: =_xlfn.XLOOKUP(C259,Customers!$A$2:$A$25,Customers!$B$2:$B$25,"not found") | N259: =_xlfn.XLOOKUP(C259,Customers!$A$2:$A$25,Customers!$D$2:$D$25,"not found")
A260: 10135 | B260: 45957 | C260: 0004 | D260: 108 | E260: 40 | F260: 290 | G260: 12 | H260: Delivered | I260: Rahul Mehta | J260: =E260*F260*(1-G260/100) | K260: =DATE(YEAR(B260),MONTH(B260),1) | L260: =IF(COUNTIF($A$2:A260,A260)=1,1,0) | M260: =_xlfn.XLOOKUP(C260,Customers!$A$2:$A$25,Customers!$B$2:$B$25,"not found") | N260: =_xlfn.XLOOKUP(C260,Customers!$A$2:$A$25,Customers!$D$2:$D$25,"not found")
A261: 10136 | B261: 45957 | C261: 0019 | D261: 108 | E261: 50 | F261: 290 | G261: 8 | H261: Delivered | I261: Farah Khan | J261: =E261*F261*(1-G261/100) | K261: =DATE(YEAR(B261),MONTH(B261),1) | L261: =IF(COUNTIF($A$2:A261,A261)=1,1,0) | M261: =_xlfn.XLOOKUP(C261,Customers!$A$2:$A$25,Customers!$B$2:$B$25,"not found") | N261: =_xlfn.XLOOKUP(C261,Customers!$A$2:$A$25,Customers!$D$2:$D$25,"not found")
A262: 10137 | B262: 45965 | C262: 0012 | D262: 108 | E262: 15 | F262: 290 | G262: 5 | H262: Delivered | I262: Neha Kulkarni | J262: =E262*F262*(1-G262/100) | K262: =DATE(YEAR(B262),MONTH(B262),1) | L262: =IF(COUNTIF($A$2:A262,A262)=1,1,0) | M262: =_xlfn.XLOOKUP(C262,Customers!$A$2:$A$25,Customers!$B$2:$B$25,"not found") | N262: =_xlfn.XLOOKUP(C262,Customers!$A$2:$A$25,Customers!$D$2:$D$25,"not found")
...

Sheet Customers
A1: customer_code | B1: customer_name | C1: city | D1: segment | E1: signup_date
A2: 0001 | B2: Sharma Hardware | C2: Mumbai | D2: Retail | E2: 45600
A3: 0002 | B3: Patel Kitchenware | C3: Ahmedabad | D3: Retail | E3: 45641
A4: 0003 | B4: Green Leaf Hotels | C4: Pune | D4: Hospitality | E4: 45543
A5: 0004 | B5: Coastal Foods | C5: Chennai | D5: Wholesale | E5: 45585
A6: 0005 | B6: Metro Mart | C6: Mumbai | D6: Retail | E6: 45648
A7: 0006 | B7: Sunrise Caterers | C7: Nagpur | D7: Hospitality | E7: 45691
A8: 0007 | B8: Northgate Distributors | C8: Delhi | D8: Wholesale | E8: 45705
A9: 0008 | B9: Blue Bay Cafe | C9: Pune | D9: Hospitality | E9: 45717
A10: 0009 | B10: Lakeview Resorts | C10: Udaipur | D10: Hospitality | E10: 45516
A11: 0010 | B11: City Needs Store | C11: Jaipur | D11: Retail | E11: 45631
A12: 0011 | B12: Harbour Traders | C12: Kochi | D12: Wholesale | E12: 45756
A13: 0012 | B13: Fresh Bowl Kitchens | C13: Bengaluru | D13: Hospitality | E13: 45708
... A25: 0024 | B25: Prime Wholesale | C25: Ahmedabad | D25: Wholesale | E25: 45971

Sheet Products
A1: product_id | B1: product_name | C1: category | D1: list_price | E1: unit_cost
A2: 101 | B2: Storage Box 10L | C2: Storage | D2: 430 | E2: 300
A3: 102 | B3: Storage Box 25L | C3: Storage | D3: 750 | E3: 540
A4: 103 | B4: Water Bottle 1L | C4: Kitchen | D4: 115 | E4: 70
A5: 104 | B5: Food Container Set | C5: Kitchen | D5: 620 | E5: 430
A6: 105 | B6: Industrial Crate | C6: Industrial | D6: 1400 | E6: 1100
A7: 106 | B7: Garden Chair | C7: Furniture | D7: 1150 | E7: 850
A8: 107 | B8: Lunch Box Set | C8: Kitchen | D8: 380 | E8: 240
A9: 108 | B9: Stackable Bin | C9: Storage | D9: 290 | E9: 190

Sheet Targets
A1: month_start | B1: target_revenue
A2: 45658 | B2: 300000
A3: 45689 | B3: 300000
A4: 45717 | B4: 320000
A5: 45748 | B5: 320000
A6: 45778 | B6: 320000
A7: 45809 | B7: 300000
A8: 45839 | B8: 280000
A9: 45870 | B9: 320000
A10: 45901 | B10: 380000
A11: 45931 | B11: 520000
A12: 45962 | B12: 500000
A13: 45992 | B13: 380000
