Workbook

Sheet Answers
A1: level | B1: item | C1: answer
A2: L1 | B2: orders | C2: =COUNT(Orders!A2:A174)
A3: L1 | B3: orders >= 25,000 | C3: =COUNTIF(Orders!D2:D174,">=25000")
A4: L2 | B4: total base points | C4: =SUM(Orders!G2:G174)
A5: L2 | B5: top customer by base points | C5: =INDEX(Customers!A2:A24,MATCH(MAX(Customers!G2:G24),Customers!G2:G24,0))
A6: L3 | B6: Gold orders | C6: =COUNTIF(Orders!I2:I174,1.5)
A7: L3 | B7: Silver orders | C7: =COUNTIF(Orders!I2:I174,1.25)
A8: L4 | B8: tier points | C8: =SUM(Orders!J2:J174)
A9: L5 | B9: streak orders | C9: =COUNTIF(Orders!K2:K174,200)
A10: L5 | B10: tier + streak points | C10: =SUM(Orders!J2:K174)
A11: L6 | B11: total order points | C11: =SUM(Orders!M2:M174)
A12: L7 | B12: customers losing points | C12: =COUNTIF(Customers!C2:C24,">0")
A13: L7 | B13: expired points | C13: =SUM(Orders!O2:O174)
A14: L8 | B14: highest balance | C14: =MAX(Customers!D2:D24)
A15: L8 | B15: customer with highest balance | C15: =INDEX(Customers!A2:A24,MATCH(MAX(Customers!D2:D24),Customers!D2:D24,0))
A16: L8 | B16: customers >= 4,000 | C16: =COUNTIF(Customers!D2:D24,">=4000")
A17: B1 | B17: first order_id reaching 5,000 | C17: =MIN(Orders!P2:P174)
A18: B1 | B18: customer | C18: =INDEX(Orders!C2:C174,MATCH(MIN(Orders!P2:P174),Orders!A2:A174,0))
A19: B2 | B19: top month points | C19: =MAX(Months!B2:B13)
A20: B2 | B20: top month | C20: =INDEX(Months!A2:A13,MATCH(MAX(Months!B2:B13),Months!B2:B13,0))
A21: B3 | B21: customers ordering every month | C21: =COUNTIF(Customers!F2:F24,12)
A22: B4 | B22: Metro Mart rank | C22: =INDEX(Customers!E2:E24,MATCH("Metro Mart",Customers!A2:A24,0))

Sheet Lines
A1: order_id | B1: order_date | C1: customer_name | D1: product_id | E1: quantity | F1: unit_price | G1: discount_pct | H1: status | I1: net_revenue
A2: 10001 | B2: 45659 | C2: Patel Kitchenware | D2: 108 | E2: 10 | F2: 290 | G2: 0 | H2: Delivered | I2: 2900
A3: 10002 | B3: 45662 | C3: Green Leaf Hotels | D3: 107 | E3: 55 | F3: 380 | G3: 0 | H3: Delivered | I3: 20900
A4: 10003 | B4: 45669 | C4: Metro Mart | D4: 101 | E4: 25 | F4: 430 | G4: 0 | H4: Delivered | I4: 10750
A5: 10003 | B5: 45669 | C5: Metro Mart | D5: 102 | E5: 45 | F5: 750 | G5: 5 | H5: Delivered | I5: 32062.5
A6: 10003 | B6: 45669 | C6: Metro Mart | D6: 108 | E6: 10 | F6: 290 | G6: 0 | H6: Delivered | I6: 2900
A7: 10004 | B7: 45670 | C7: Metro Mart | D7: 101 | E7: 40 | F7: 430 | G7: 0 | H7: Delivered | I7: 17200
A8: 10004 | B8: 45670 | C8: Metro Mart | D8: 102 | E8: 15 | F8: 750 | G8: 5 | H8: Delivered | I8: 10687.5
A9: 10005 | B9: 45677 | C9: Green Leaf Hotels | D9: 101 | E9: 15 | F9: 430 | G9: 5 | H9: Delivered | I9: 6127.5
A10: 10006 | B10: 45678 | C10: Coastal Foods | D10: 102 | E10: 25 | F10: 750 | G10: 5 | H10: Delivered | I10: 17812.5
A11: 10007 | B11: 45681 | C11: Sharma Hardware | D11: 101 | E11: 45 | F11: 430 | G11: 0 | H11: Delivered | I11: 19350
A12: 10007 | B12: 45681 | C12: Sharma Hardware | D12: 102 | E12: 20 | F12: 750 | G12: 0 | H12: Delivered | I12: 15000
A13: 10007 | B13: 45681 | C13: Sharma Hardware | D13: 108 | E13: 20 | F13: 290 | G13: 0 | H13: Delivered | I13: 5800
... A331: 10175 | B331: 46014 | C331: Royal Banquets | D331: 108 | E331: 30 | F331: 290 | G331: 0 | H331: Shipped | I331: 8700

Sheet Orders
A1: order_id | B1: order_date | C1: customer | D1: value | E1: lines | F1: month | G1: base | H1: prev_spend | I1: multiplier | J1: tier_points | K1: streak | L1: basket | M1: points | N1: running_points | O1: expired | P1: hit_5000
A2: 10001 | B2: =INDEX(Lines!$B$2:$B$331,MATCH(A2,Lines!$A$2:$A$331,0)) | C2: =INDEX(Lines!$C$2:$C$331,MATCH(A2,Lines!$A$2:$A$331,0)) | D2: =SUMIFS(Lines!$I$2:$I$331,Lines!$A$2:$A$331,A2) | E2: =COUNTIFS(Lines!$A$2:$A$331,A2) | F2: =DATE(YEAR(B2),MONTH(B2),1) | G2: =INT(D2/100) | H2: =SUMIFS($D$2:D2,$C$2:C2,C2)-D2 | I2: =IF(H2>=250000,1.5,IF(H2>=100000,1.25,1)) | J2: =ROUNDDOWN(G2*I2,0) | K2: =IF(COUNTIFS($C$2:$C$174,C2,$F$2:$F$174,EDATE(F2,-1))>0,200,0) | L2: =IF(E2>=3,100,0) | M2: =J2+K2+L2 | N2: =SUMIFS($M$2:M2,$C$2:C2,C2) | O2: =IF(AND(B2<DATE(2025,7,1),COUNTIFS($C$2:$C$174,C2,$B$2:$B$174,">="&DATE(2025,10,1))=0),M2,0) | P2: =IF(N2>=5000,A2,"")
A3: 10002 | B3: =INDEX(Lines!$B$2:$B$331,MATCH(A3,Lines!$A$2:$A$331,0)) | C3: =INDEX(Lines!$C$2:$C$331,MATCH(A3,Lines!$A$2:$A$331,0)) | D3: =SUMIFS(Lines!$I$2:$I$331,Lines!$A$2:$A$331,A3) | E3: =COUNTIFS(Lines!$A$2:$A$331,A3) | F3: =DATE(YEAR(B3),MONTH(B3),1) | G3: =INT(D3/100) | H3: =SUMIFS($D$2:D3,$C$2:C3,C3)-D3 | I3: =IF(H3>=250000,1.5,IF(H3>=100000,1.25,1)) | J3: =ROUNDDOWN(G3*I3,0) | K3: =IF(COUNTIFS($C$2:$C$174,C3,$F$2:$F$174,EDATE(F3,-1))>0,200,0) | L3: =IF(E3>=3,100,0) | M3: =J3+K3+L3 | N3: =SUMIFS($M$2:M3,$C$2:C3,C3) | O3: =IF(AND(B3<DATE(2025,7,1),COUNTIFS($C$2:$C$174,C3,$B$2:$B$174,">="&DATE(2025,10,1))=0),M3,0) | P3: =IF(N3>=5000,A3,"")
A4: 10003 | B4: =INDEX(Lines!$B$2:$B$331,MATCH(A4,Lines!$A$2:$A$331,0)) | C4: =INDEX(Lines!$C$2:$C$331,MATCH(A4,Lines!$A$2:$A$331,0)) | D4: =SUMIFS(Lines!$I$2:$I$331,Lines!$A$2:$A$331,A4) | E4: =COUNTIFS(Lines!$A$2:$A$331,A4) | F4: =DATE(YEAR(B4),MONTH(B4),1) | G4: =INT(D4/100) | H4: =SUMIFS($D$2:D4,$C$2:C4,C4)-D4 | I4: =IF(H4>=250000,1.5,IF(H4>=100000,1.25,1)) | J4: =ROUNDDOWN(G4*I4,0) | K4: =IF(COUNTIFS($C$2:$C$174,C4,$F$2:$F$174,EDATE(F4,-1))>0,200,0) | L4: =IF(E4>=3,100,0) | M4: =J4+K4+L4 | N4: =SUMIFS($M$2:M4,$C$2:C4,C4) | O4: =IF(AND(B4<DATE(2025,7,1),COUNTIFS($C$2:$C$174,C4,$B$2:$B$174,">="&DATE(2025,10,1))=0),M4,0) | P4: =IF(N4>=5000,A4,"")
A5: 10004 | B5: =INDEX(Lines!$B$2:$B$331,MATCH(A5,Lines!$A$2:$A$331,0)) | C5: =INDEX(Lines!$C$2:$C$331,MATCH(A5,Lines!$A$2:$A$331,0)) | D5: =SUMIFS(Lines!$I$2:$I$331,Lines!$A$2:$A$331,A5) | E5: =COUNTIFS(Lines!$A$2:$A$331,A5) | F5: =DATE(YEAR(B5),MONTH(B5),1) | G5: =INT(D5/100) | H5: =SUMIFS($D$2:D5,$C$2:C5,C5)-D5 | I5: =IF(H5>=250000,1.5,IF(H5>=100000,1.25,1)) | J5: =ROUNDDOWN(G5*I5,0) | K5: =IF(COUNTIFS($C$2:$C$174,C5,$F$2:$F$174,EDATE(F5,-1))>0,200,0) | L5: =IF(E5>=3,100,0) | M5: =J5+K5+L5 | N5: =SUMIFS($M$2:M5,$C$2:C5,C5) | O5: =IF(AND(B5<DATE(2025,7,1),COUNTIFS($C$2:$C$174,C5,$B$2:$B$174,">="&DATE(2025,10,1))=0),M5,0) | P5: =IF(N5>=5000,A5,"")
A6: 10005 | B6: =INDEX(Lines!$B$2:$B$331,MATCH(A6,Lines!$A$2:$A$331,0)) | C6: =INDEX(Lines!$C$2:$C$331,MATCH(A6,Lines!$A$2:$A$331,0)) | D6: =SUMIFS(Lines!$I$2:$I$331,Lines!$A$2:$A$331,A6) | E6: =COUNTIFS(Lines!$A$2:$A$331,A6) | F6: =DATE(YEAR(B6),MONTH(B6),1) | G6: =INT(D6/100) | H6: =SUMIFS($D$2:D6,$C$2:C6,C6)-D6 | I6: =IF(H6>=250000,1.5,IF(H6>=100000,1.25,1)) | J6: =ROUNDDOWN(G6*I6,0) | K6: =IF(COUNTIFS($C$2:$C$174,C6,$F$2:$F$174,EDATE(F6,-1))>0,200,0) | L6: =IF(E6>=3,100,0) | M6: =J6+K6+L6 | N6: =SUMIFS($M$2:M6,$C$2:C6,C6) | O6: =IF(AND(B6<DATE(2025,7,1),COUNTIFS($C$2:$C$174,C6,$B$2:$B$174,">="&DATE(2025,10,1))=0),M6,0) | P6: =IF(N6>=5000,A6,"")
A7: 10006 | B7: =INDEX(Lines!$B$2:$B$331,MATCH(A7,Lines!$A$2:$A$331,0)) | C7: =INDEX(Lines!$C$2:$C$331,MATCH(A7,Lines!$A$2:$A$331,0)) | D7: =SUMIFS(Lines!$I$2:$I$331,Lines!$A$2:$A$331,A7) | E7: =COUNTIFS(Lines!$A$2:$A$331,A7) | F7: =DATE(YEAR(B7),MONTH(B7),1) | G7: =INT(D7/100) | H7: =SUMIFS($D$2:D7,$C$2:C7,C7)-D7 | I7: =IF(H7>=250000,1.5,IF(H7>=100000,1.25,1)) | J7: =ROUNDDOWN(G7*I7,0) | K7: =IF(COUNTIFS($C$2:$C$174,C7,$F$2:$F$174,EDATE(F7,-1))>0,200,0) | L7: =IF(E7>=3,100,0) | M7: =J7+K7+L7 | N7: =SUMIFS($M$2:M7,$C$2:C7,C7) | O7: =IF(AND(B7<DATE(2025,7,1),COUNTIFS($C$2:$C$174,C7,$B$2:$B$174,">="&DATE(2025,10,1))=0),M7,0) | P7: =IF(N7>=5000,A7,"")
A8: 10007 | B8: =INDEX(Lines!$B$2:$B$331,MATCH(A8,Lines!$A$2:$A$331,0)) | C8: =INDEX(Lines!$C$2:$C$331,MATCH(A8,Lines!$A$2:$A$331,0)) | D8: =SUMIFS(Lines!$I$2:$I$331,Lines!$A$2:$A$331,A8) | E8: =COUNTIFS(Lines!$A$2:$A$331,A8) | F8: =DATE(YEAR(B8),MONTH(B8),1) | G8: =INT(D8/100) | H8: =SUMIFS($D$2:D8,$C$2:C8,C8)-D8 | I8: =IF(H8>=250000,1.5,IF(H8>=100000,1.25,1)) | J8: =ROUNDDOWN(G8*I8,0) | K8: =IF(COUNTIFS($C$2:$C$174,C8,$F$2:$F$174,EDATE(F8,-1))>0,200,0) | L8: =IF(E8>=3,100,0) | M8: =J8+K8+L8 | N8: =SUMIFS($M$2:M8,$C$2:C8,C8) | O8: =IF(AND(B8<DATE(2025,7,1),COUNTIFS($C$2:$C$174,C8,$B$2:$B$174,">="&DATE(2025,10,1))=0),M8,0) | P8: =IF(N8>=5000,A8,"")
A9: 10008 | B9: =INDEX(Lines!$B$2:$B$331,MATCH(A9,Lines!$A$2:$A$331,0)) | C9: =INDEX(Lines!$C$2:$C$331,MATCH(A9,Lines!$A$2:$A$331,0)) | D9: =SUMIFS(Lines!$I$2:$I$331,Lines!$A$2:$A$331,A9) | E9: =COUNTIFS(Lines!$A$2:$A$331,A9) | F9: =DATE(YEAR(B9),MONTH(B9),1) | G9: =INT(D9/100) | H9: =SUMIFS($D$2:D9,$C$2:C9,C9)-D9 | I9: =IF(H9>=250000,1.5,IF(H9>=100000,1.25,1)) | J9: =ROUNDDOWN(G9*I9,0) | K9: =IF(COUNTIFS($C$2:$C$174,C9,$F$2:$F$174,EDATE(F9,-1))>0,200,0) | L9: =IF(E9>=3,100,0) | M9: =J9+K9+L9 | N9: =SUMIFS($M$2:M9,$C$2:C9,C9) | O9: =IF(AND(B9<DATE(2025,7,1),COUNTIFS($C$2:$C$174,C9,$B$2:$B$174,">="&DATE(2025,10,1))=0),M9,0) | P9: =IF(N9>=5000,A9,"")
A10: 10009 | B10: =INDEX(Lines!$B$2:$B$331,MATCH(A10,Lines!$A$2:$A$331,0)) | C10: =INDEX(Lines!$C$2:$C$331,MATCH(A10,Lines!$A$2:$A$331,0)) | D10: =SUMIFS(Lines!$I$2:$I$331,Lines!$A$2:$A$331,A10) | E10: =COUNTIFS(Lines!$A$2:$A$331,A10) | F10: =DATE(YEAR(B10),MONTH(B10),1) | G10: =INT(D10/100) | H10: =SUMIFS($D$2:D10,$C$2:C10,C10)-D10 | I10: =IF(H10>=250000,1.5,IF(H10>=100000,1.25,1)) | J10: =ROUNDDOWN(G10*I10,0) | K10: =IF(COUNTIFS($C$2:$C$174,C10,$F$2:$F$174,EDATE(F10,-1))>0,200,0) | L10: =IF(E10>=3,100,0) | M10: =J10+K10+L10 | N10: =SUMIFS($M$2:M10,$C$2:C10,C10) | O10: =IF(AND(B10<DATE(2025,7,1),COUNTIFS($C$2:$C$174,C10,$B$2:$B$174,">="&DATE(2025,10,1))=0),M10,0) | P10: =IF(N10>=5000,A10,"")
A11: 10010 | B11: =INDEX(Lines!$B$2:$B$331,MATCH(A11,Lines!$A$2:$A$331,0)) | C11: =INDEX(Lines!$C$2:$C$331,MATCH(A11,Lines!$A$2:$A$331,0)) | D11: =SUMIFS(Lines!$I$2:$I$331,Lines!$A$2:$A$331,A11) | E11: =COUNTIFS(Lines!$A$2:$A$331,A11) | F11: =DATE(YEAR(B11),MONTH(B11),1) | G11: =INT(D11/100) | H11: =SUMIFS($D$2:D11,$C$2:C11,C11)-D11 | I11: =IF(H11>=250000,1.5,IF(H11>=100000,1.25,1)) | J11: =ROUNDDOWN(G11*I11,0) | K11: =IF(COUNTIFS($C$2:$C$174,C11,$F$2:$F$174,EDATE(F11,-1))>0,200,0) | L11: =IF(E11>=3,100,0) | M11: =J11+K11+L11 | N11: =SUMIFS($M$2:M11,$C$2:C11,C11) | O11: =IF(AND(B11<DATE(2025,7,1),COUNTIFS($C$2:$C$174,C11,$B$2:$B$174,">="&DATE(2025,10,1))=0),M11,0) | P11: =IF(N11>=5000,A11,"")
A12: 10011 | B12: =INDEX(Lines!$B$2:$B$331,MATCH(A12,Lines!$A$2:$A$331,0)) | C12: =INDEX(Lines!$C$2:$C$331,MATCH(A12,Lines!$A$2:$A$331,0)) | D12: =SUMIFS(Lines!$I$2:$I$331,Lines!$A$2:$A$331,A12) | E12: =COUNTIFS(Lines!$A$2:$A$331,A12) | F12: =DATE(YEAR(B12),MONTH(B12),1) | G12: =INT(D12/100) | H12: =SUMIFS($D$2:D12,$C$2:C12,C12)-D12 | I12: =IF(H12>=250000,1.5,IF(H12>=100000,1.25,1)) | J12: =ROUNDDOWN(G12*I12,0) | K12: =IF(COUNTIFS($C$2:$C$174,C12,$F$2:$F$174,EDATE(F12,-1))>0,200,0) | L12: =IF(E12>=3,100,0) | M12: =J12+K12+L12 | N12: =SUMIFS($M$2:M12,$C$2:C12,C12) | O12: =IF(AND(B12<DATE(2025,7,1),COUNTIFS($C$2:$C$174,C12,$B$2:$B$174,">="&DATE(2025,10,1))=0),M12,0) | P12: =IF(N12>=5000,A12,"")
A13: 10012 | B13: =INDEX(Lines!$B$2:$B$331,MATCH(A13,Lines!$A$2:$A$331,0)) | C13: =INDEX(Lines!$C$2:$C$331,MATCH(A13,Lines!$A$2:$A$331,0)) | D13: =SUMIFS(Lines!$I$2:$I$331,Lines!$A$2:$A$331,A13) | E13: =COUNTIFS(Lines!$A$2:$A$331,A13) | F13: =DATE(YEAR(B13),MONTH(B13),1) | G13: =INT(D13/100) | H13: =SUMIFS($D$2:D13,$C$2:C13,C13)-D13 | I13: =IF(H13>=250000,1.5,IF(H13>=100000,1.25,1)) | J13: =ROUNDDOWN(G13*I13,0) | K13: =IF(COUNTIFS($C$2:$C$174,C13,$F$2:$F$174,EDATE(F13,-1))>0,200,0) | L13: =IF(E13>=3,100,0) | M13: =J13+K13+L13 | N13: =SUMIFS($M$2:M13,$C$2:C13,C13) | O13: =IF(AND(B13<DATE(2025,7,1),COUNTIFS($C$2:$C$174,C13,$B$2:$B$174,">="&DATE(2025,10,1))=0),M13,0) | P13: =IF(N13>=5000,A13,"")
... A174: 10175 | B174: =INDEX(Lines!$B$2:$B$331,MATCH(A174,Lines!$A$2:$A$331,0)) | C174: =INDEX(Lines!$C$2:$C$331,MATCH(A174,Lines!$A$2:$A$331,0)) | D174: =SUMIFS(Lines!$I$2:$I$331,Lines!$A$2:$A$331,A174) | E174: =COUNTIFS(Lines!$A$2:$A$331,A174) | F174: =DATE(YEAR(B174),MONTH(B174),1) | G174: =INT(D174/100) | H174: =SUMIFS($D$2:D174,$C$2:C174,C174)-D174 | I174: =IF(H174>=250000,1.5,IF(H174>=100000,1.25,1)) | J174: =ROUNDDOWN(G174*I174,0) | K174: =IF(COUNTIFS($C$2:$C$174,C174,$F$2:$F$174,EDATE(F174,-1))>0,200,0) | L174: =IF(E174>=3,100,0) | M174: =J174+K174+L174 | N174: =SUMIFS($M$2:M174,$C$2:C174,C174) | O174: =IF(AND(B174<DATE(2025,7,1),COUNTIFS($C$2:$C$174,C174,$B$2:$B$174,">="&DATE(2025,10,1))=0),M174,0) | P174: =IF(N174>=5000,A174,"")

Sheet Customers
A1: customer | B1: points | C1: expired | D1: balance | E1: rank | F1: months_ordered | G1: base_points
A2: Blue Bay Cafe | B2: =SUMIFS(Orders!$M$2:$M$174,Orders!$C$2:$C$174,A2) | C2: =SUMIFS(Orders!$O$2:$O$174,Orders!$C$2:$C$174,A2) | D2: =B2-C2 | E2: =RANK(D2,$D$2:$D$24,0) | F2: =SUMPRODUCT((Orders!$C$2:$C$174=A2)/COUNTIFS(Orders!$C$2:$C$174,Orders!$C$2:$C$174,Orders!$F$2:$F$174,Orders!$F$2:$F$174)) | G2: =SUMIFS(Orders!$G$2:$G$174,Orders!$C$2:$C$174,A2)
A3: City Needs Store | B3: =SUMIFS(Orders!$M$2:$M$174,Orders!$C$2:$C$174,A3) | C3: =SUMIFS(Orders!$O$2:$O$174,Orders!$C$2:$C$174,A3) | D3: =B3-C3 | E3: =RANK(D3,$D$2:$D$24,0) | F3: =SUMPRODUCT((Orders!$C$2:$C$174=A3)/COUNTIFS(Orders!$C$2:$C$174,Orders!$C$2:$C$174,Orders!$F$2:$F$174,Orders!$F$2:$F$174)) | G3: =SUMIFS(Orders!$G$2:$G$174,Orders!$C$2:$C$174,A3)
A4: Coastal Foods | B4: =SUMIFS(Orders!$M$2:$M$174,Orders!$C$2:$C$174,A4) | C4: =SUMIFS(Orders!$O$2:$O$174,Orders!$C$2:$C$174,A4) | D4: =B4-C4 | E4: =RANK(D4,$D$2:$D$24,0) | F4: =SUMPRODUCT((Orders!$C$2:$C$174=A4)/COUNTIFS(Orders!$C$2:$C$174,Orders!$C$2:$C$174,Orders!$F$2:$F$174,Orders!$F$2:$F$174)) | G4: =SUMIFS(Orders!$G$2:$G$174,Orders!$C$2:$C$174,A4)
A5: Deccan Packaging | B5: =SUMIFS(Orders!$M$2:$M$174,Orders!$C$2:$C$174,A5) | C5: =SUMIFS(Orders!$O$2:$O$174,Orders!$C$2:$C$174,A5) | D5: =B5-C5 | E5: =RANK(D5,$D$2:$D$24,0) | F5: =SUMPRODUCT((Orders!$C$2:$C$174=A5)/COUNTIFS(Orders!$C$2:$C$174,Orders!$C$2:$C$174,Orders!$F$2:$F$174,Orders!$F$2:$F$174)) | G5: =SUMIFS(Orders!$G$2:$G$174,Orders!$C$2:$C$174,A5)
A6: Evergreen Mart | B6: =SUMIFS(Orders!$M$2:$M$174,Orders!$C$2:$C$174,A6) | C6: =SUMIFS(Orders!$O$2:$O$174,Orders!$C$2:$C$174,A6) | D6: =B6-C6 | E6: =RANK(D6,$D$2:$D$24,0) | F6: =SUMPRODUCT((Orders!$C$2:$C$174=A6)/COUNTIFS(Orders!$C$2:$C$174,Orders!$C$2:$C$174,Orders!$F$2:$F$174,Orders!$F$2:$F$174)) | G6: =SUMIFS(Orders!$G$2:$G$174,Orders!$C$2:$C$174,A6)
A7: Festive Gifts Co | B7: =SUMIFS(Orders!$M$2:$M$174,Orders!$C$2:$C$174,A7) | C7: =SUMIFS(Orders!$O$2:$O$174,Orders!$C$2:$C$174,A7) | D7: =B7-C7 | E7: =RANK(D7,$D$2:$D$24,0) | F7: =SUMPRODUCT((Orders!$C$2:$C$174=A7)/COUNTIFS(Orders!$C$2:$C$174,Orders!$C$2:$C$174,Orders!$F$2:$F$174,Orders!$F$2:$F$174)) | G7: =SUMIFS(Orders!$G$2:$G$174,Orders!$C$2:$C$174,A7)
A8: Fresh Bowl Kitchens | B8: =SUMIFS(Orders!$M$2:$M$174,Orders!$C$2:$C$174,A8) | C8: =SUMIFS(Orders!$O$2:$O$174,Orders!$C$2:$C$174,A8) | D8: =B8-C8 | E8: =RANK(D8,$D$2:$D$24,0) | F8: =SUMPRODUCT((Orders!$C$2:$C$174=A8)/COUNTIFS(Orders!$C$2:$C$174,Orders!$C$2:$C$174,Orders!$F$2:$F$174,Orders!$F$2:$F$174)) | G8: =SUMIFS(Orders!$G$2:$G$174,Orders!$C$2:$C$174,A8)
A9: Green Leaf Hotels | B9: =SUMIFS(Orders!$M$2:$M$174,Orders!$C$2:$C$174,A9) | C9: =SUMIFS(Orders!$O$2:$O$174,Orders!$C$2:$C$174,A9) | D9: =B9-C9 | E9: =RANK(D9,$D$2:$D$24,0) | F9: =SUMPRODUCT((Orders!$C$2:$C$174=A9)/COUNTIFS(Orders!$C$2:$C$174,Orders!$C$2:$C$174,Orders!$F$2:$F$174,Orders!$F$2:$F$174)) | G9: =SUMIFS(Orders!$G$2:$G$174,Orders!$C$2:$C$174,A9)
A10: Harbour Traders | B10: =SUMIFS(Orders!$M$2:$M$174,Orders!$C$2:$C$174,A10) | C10: =SUMIFS(Orders!$O$2:$O$174,Orders!$C$2:$C$174,A10) | D10: =B10-C10 | E10: =RANK(D10,$D$2:$D$24,0) | F10: =SUMPRODUCT((Orders!$C$2:$C$174=A10)/COUNTIFS(Orders!$C$2:$C$174,Orders!$C$2:$C$174,Orders!$F$2:$F$174,Orders!$F$2:$F$174)) | G10: =SUMIFS(Orders!$G$2:$G$174,Orders!$C$2:$C$174,A10)
A11: Kitchen Kraft | B11: =SUMIFS(Orders!$M$2:$M$174,Orders!$C$2:$C$174,A11) | C11: =SUMIFS(Orders!$O$2:$O$174,Orders!$C$2:$C$174,A11) | D11: =B11-C11 | E11: =RANK(D11,$D$2:$D$24,0) | F11: =SUMPRODUCT((Orders!$C$2:$C$174=A11)/COUNTIFS(Orders!$C$2:$C$174,Orders!$C$2:$C$174,Orders!$F$2:$F$174,Orders!$F$2:$F$174)) | G11: =SUMIFS(Orders!$G$2:$G$174,Orders!$C$2:$C$174,A11)
A12: Lakeview Resorts | B12: =SUMIFS(Orders!$M$2:$M$174,Orders!$C$2:$C$174,A12) | C12: =SUMIFS(Orders!$O$2:$O$174,Orders!$C$2:$C$174,A12) | D12: =B12-C12 | E12: =RANK(D12,$D$2:$D$24,0) | F12: =SUMPRODUCT((Orders!$C$2:$C$174=A12)/COUNTIFS(Orders!$C$2:$C$174,Orders!$C$2:$C$174,Orders!$F$2:$F$174,Orders!$F$2:$F$174)) | G12: =SUMIFS(Orders!$G$2:$G$174,Orders!$C$2:$C$174,A12)
A13: Metro Mart | B13: =SUMIFS(Orders!$M$2:$M$174,Orders!$C$2:$C$174,A13) | C13: =SUMIFS(Orders!$O$2:$O$174,Orders!$C$2:$C$174,A13) | D13: =B13-C13 | E13: =RANK(D13,$D$2:$D$24,0) | F13: =SUMPRODUCT((Orders!$C$2:$C$174=A13)/COUNTIFS(Orders!$C$2:$C$174,Orders!$C$2:$C$174,Orders!$F$2:$F$174,Orders!$F$2:$F$174)) | G13: =SUMIFS(Orders!$G$2:$G$174,Orders!$C$2:$C$174,A13)
... A24: Western Logistics | B24: =SUMIFS(Orders!$M$2:$M$174,Orders!$C$2:$C$174,A24) | C24: =SUMIFS(Orders!$O$2:$O$174,Orders!$C$2:$C$174,A24) | D24: =B24-C24 | E24: =RANK(D24,$D$2:$D$24,0) | F24: =SUMPRODUCT((Orders!$C$2:$C$174=A24)/COUNTIFS(Orders!$C$2:$C$174,Orders!$C$2:$C$174,Orders!$F$2:$F$174,Orders!$F$2:$F$174)) | G24: =SUMIFS(Orders!$G$2:$G$174,Orders!$C$2:$C$174,A24)

Sheet Months
A1: month | B1: points
A2: 45658 | B2: =SUMIFS(Orders!$M$2:$M$174,Orders!$F$2:$F$174,A2)
A3: 45689 | B3: =SUMIFS(Orders!$M$2:$M$174,Orders!$F$2:$F$174,A3)
A4: 45717 | B4: =SUMIFS(Orders!$M$2:$M$174,Orders!$F$2:$F$174,A4)
A5: 45748 | B5: =SUMIFS(Orders!$M$2:$M$174,Orders!$F$2:$F$174,A5)
A6: 45778 | B6: =SUMIFS(Orders!$M$2:$M$174,Orders!$F$2:$F$174,A6)
A7: 45809 | B7: =SUMIFS(Orders!$M$2:$M$174,Orders!$F$2:$F$174,A7)
A8: 45839 | B8: =SUMIFS(Orders!$M$2:$M$174,Orders!$F$2:$F$174,A8)
A9: 45870 | B9: =SUMIFS(Orders!$M$2:$M$174,Orders!$F$2:$F$174,A9)
A10: 45901 | B10: =SUMIFS(Orders!$M$2:$M$174,Orders!$F$2:$F$174,A10)
A11: 45931 | B11: =SUMIFS(Orders!$M$2:$M$174,Orders!$F$2:$F$174,A11)
A12: 45962 | B12: =SUMIFS(Orders!$M$2:$M$174,Orders!$F$2:$F$174,A12)
A13: 45992 | B13: =SUMIFS(Orders!$M$2:$M$174,Orders!$F$2:$F$174,A13)
